{
  "run_id": "R12_00005_2025_interim_report_zh",
  "case_id": "R12_00005_2025_interim_report_zh",
  "state_id": "S5_TranslationPlan",
  "decision_id": "D2_translation",
  "batch_id": "batch_0010",
  "batch_index": 10,
  "batch_count": 22,
  "source_extraction_ref": "docs/reports/round12/R12_00005_2025_interim_report_zh/source_extraction.json",
  "source_language": "zh",
  "target_language": "en",
  "target_text_field": "translation_en",
  "translation_units": [
    {
      "unit_id": "p4_b4_l2",
      "page_index": 4,
      "block_id": 4,
      "line_index": 2,
      "source_text": "已減值之",
      "bbox": [
        484.72,
        110.18,
        512.72,
        119.491
      ],
      "page_rect": [
        0.0,
        0.0,
        595.28,
        841.89
      ],
      "font_size": 7.0,
      "font": "MicrosoftJhengHeiBold",
      "ascii_tokens": [],
      "cjk_char_count": 4,
      "preserve_tokens": [],
      "layout_hint": "short_label"
    },
    {
      "unit_id": "p4_b4_l3",
      "page_index": 4,
      "block_id": 4,
      "line_index": 3,
      "source_text": "⾦融資產",
      "bbox": [
        484.72,
        118.58,
        512.72,
        127.891
      ],
      "page_rect": [
        0.0,
        0.0,
        595.28,
        841.89
      ],
      "font_size": 7.0,
      "font": "MicrosoftJhengHeiBold",
      "ascii_tokens": [],
      "cjk_char_count": 3,
      "preserve_tokens": [],
      "layout_hint": "short_label"
    },
    {
      "unit_id": "p4_b4_l4",
      "page_index": 4,
      "block_id": 4,
      "line_index": 4,
      "source_text": "總計",
      "bbox": [
        536.97,
        118.58,
        550.97,
        127.891
      ],
      "page_rect": [
        0.0,
        0.0,
        595.28,
        841.89
      ],
      "font_size": 7.0,
      "font": "MicrosoftJhengHeiBold",
      "ascii_tokens": [],
      "cjk_char_count": 2,
      "preserve_tokens": [],
      "layout_hint": "short_label"
    },
    {
      "unit_id": "p4_b4_l5",
      "page_index": 4,
      "block_id": 4,
      "line_index": 5,
      "source_text": "百萬美元",
      "bbox": [
        178.72,
        128.33,
        206.72,
        137.641
      ],
      "page_rect": [
        0.0,
        0.0,
        595.28,
        841.89
      ],
      "font_size": 7.0,
      "font": "MicrosoftJhengHeiBold",
      "ascii_tokens": [],
      "cjk_char_count": 4,
      "preserve_tokens": [],
      "layout_hint": "short_label"
    },
    {
      "unit_id": "p4_b4_l6",
      "page_index": 4,
      "block_id": 4,
      "line_index": 6,
      "source_text": "百萬美元",
      "bbox": [
        216.97,
        128.33,
        244.97,
        137.641
      ],
      "page_rect": [
        0.0,
        0.0,
        595.28,
        841.89
      ],
      "font_size": 7.0,
      "font": "MicrosoftJhengHeiBold",
      "ascii_tokens": [],
      "cjk_char_count": 4,
      "preserve_tokens": [],
      "layout_hint": "short_label"
    },
    {
      "unit_id": "p4_b4_l7",
      "page_index": 4,
      "block_id": 4,
      "line_index": 7,
      "source_text": "百萬美元",
      "bbox": [
        255.22,
        128.33,
        283.22,
        137.641
      ],
      "page_rect": [
        0.0,
        0.0,
        595.28,
        841.89
      ],
      "font_size": 7.0,
      "font": "MicrosoftJhengHeiBold",
      "ascii_tokens": [],
      "cjk_char_count": 4,
      "preserve_tokens": [],
      "layout_hint": "short_label"
    },
    {
      "unit_id": "p4_b4_l8",
      "page_index": 4,
      "block_id": 4,
      "line_index": 8,
      "source_text": "百萬美元",
      "bbox": [
        293.47,
        128.33,
        321.47,
        137.641
      ],
      "page_rect": [
        0.0,
        0.0,
        595.28,
        841.89
      ],
      "font_size": 7.0,
      "font": "MicrosoftJhengHeiBold",
      "ascii_tokens": [],
      "cjk_char_count": 4,
      "preserve_tokens": [],
      "layout_hint": "short_label"
    },
    {
      "unit_id": "p4_b4_l9",
      "page_index": 4,
      "block_id": 4,
      "line_index": 9,
      "source_text": "百萬美元",
      "bbox": [
        331.72,
        128.33,
        359.72,
        137.641
      ],
      "page_rect": [
        0.0,
        0.0,
        595.28,
        841.89
      ],
      "font_size": 7.0,
      "font": "MicrosoftJhengHeiBold",
      "ascii_tokens": [],
      "cjk_char_count": 4,
      "preserve_tokens": [],
      "layout_hint": "short_label"
    },
    {
      "unit_id": "p4_b4_l10",
      "page_index": 4,
      "block_id": 4,
      "line_index": 10,
      "source_text": "百萬美元",
      "bbox": [
        369.97,
        128.33,
        397.97,
        137.641
      ],
      "page_rect": [
        0.0,
        0.0,
        595.28,
        841.89
      ],
      "font_size": 7.0,
      "font": "MicrosoftJhengHeiBold",
      "ascii_tokens": [],
      "cjk_char_count": 4,
      "preserve_tokens": [],
      "layout_hint": "short_label"
    },
    {
      "unit_id": "p4_b4_l11",
      "page_index": 4,
      "block_id": 4,
      "line_index": 11,
      "source_text": "百萬美元",
      "bbox": [
        408.22,
        128.33,
        436.22,
        137.641
      ],
      "page_rect": [
        0.0,
        0.0,
        595.28,
        841.89
      ],
      "font_size": 7.0,
      "font": "MicrosoftJhengHeiBold",
      "ascii_tokens": [],
      "cjk_char_count": 4,
      "preserve_tokens": [],
      "layout_hint": "short_label"
    },
    {
      "unit_id": "p4_b4_l12",
      "page_index": 4,
      "block_id": 4,
      "line_index": 12,
      "source_text": "百萬美元",
      "bbox": [
        446.47,
        128.33,
        474.47,
        137.641
      ],
      "page_rect": [
        0.0,
        0.0,
        595.28,
        841.89
      ],
      "font_size": 7.0,
      "font": "MicrosoftJhengHeiBold",
      "ascii_tokens": [],
      "cjk_char_count": 4,
      "preserve_tokens": [],
      "layout_hint": "short_label"
    },
    {
      "unit_id": "p4_b4_l13",
      "page_index": 4,
      "block_id": 4,
      "line_index": 13,
      "source_text": "百萬美元",
      "bbox": [
        484.72,
        128.33,
        512.72,
        137.641
      ],
      "page_rect": [
        0.0,
        0.0,
        595.28,
        841.89
      ],
      "font_size": 7.0,
      "font": "MicrosoftJhengHeiBold",
      "ascii_tokens": [],
      "cjk_char_count": 4,
      "preserve_tokens": [],
      "layout_hint": "short_label"
    },
    {
      "unit_id": "p4_b4_l14",
      "page_index": 4,
      "block_id": 4,
      "line_index": 14,
      "source_text": "百萬美元",
      "bbox": [
        522.97,
        128.33,
        550.97,
        137.641
      ],
      "page_rect": [
        0.0,
        0.0,
        595.28,
        841.89
      ],
      "font_size": 7.0,
      "font": "MicrosoftJhengHeiBold",
      "ascii_tokens": [],
      "cjk_char_count": 4,
      "preserve_tokens": [],
      "layout_hint": "short_label"
    },
    {
      "unit_id": "p4_b4_l15",
      "page_index": 4,
      "block_id": 4,
      "line_index": 15,
      "source_text": "企業及商業貸款",
      "bbox": [
        43.98,
        138.08,
        92.98,
        147.391
      ],
      "page_rect": [
        0.0,
        0.0,
        595.28,
        841.89
      ],
      "font_size": 7.0,
      "font": "MicrosoftJhengHeiRegular",
      "ascii_tokens": [],
      "cjk_char_count": 7,
      "preserve_tokens": [],
      "layout_hint": "short_label"
    },
    {
      "unit_id": "p4_b4_l25",
      "page_index": 4,
      "block_id": 4,
      "line_index": 25,
      "source_text": "⾦融機構",
      "bbox": [
        43.98,
        147.83,
        71.98,
        157.141
      ],
      "page_rect": [
        0.0,
        0.0,
        595.28,
        841.89
      ],
      "font_size": 7.0,
      "font": "MicrosoftJhengHeiRegular",
      "ascii_tokens": [],
      "cjk_char_count": 3,
      "preserve_tokens": [],
      "layout_hint": "short_label"
    },
    {
      "unit_id": "p4_b4_l35",
      "page_index": 4,
      "block_id": 4,
      "line_index": 35,
      "source_text": "於2025年6⽉30⽇",
      "bbox": [
        43.98,
        157.58,
        101.135,
        166.891
      ],
      "page_rect": [
        0.0,
        0.0,
        595.28,
        841.89
      ],
      "font_size": 7.0,
      "font": "MicrosoftJhengHeiBold",
      "ascii_tokens": [],
      "cjk_char_count": 2,
      "preserve_tokens": [
        {
          "type": "currency_amount",
          "value": "30"
        }
      ],
      "layout_hint": "short_label"
    },
    {
      "unit_id": "p4_b4_l46",
      "page_index": 4,
      "block_id": 4,
      "line_index": 46,
      "source_text": "按法律實體列⽰",
      "bbox": [
        43.98,
        167.33,
        92.98,
        176.641
      ],
      "page_rect": [
        0.0,
        0.0,
        595.28,
        841.89
      ],
      "font_size": 7.0,
      "font": "MicrosoftJhengHeiBold",
      "ascii_tokens": [],
      "cjk_char_count": 6,
      "preserve_tokens": [],
      "layout_hint": "short_label"
    },
    {
      "unit_id": "p4_b4_l59",
      "page_index": 4,
      "block_id": 4,
      "line_index": 59,
      "source_text": "英國滙豐銀⾏有限公司",
      "bbox": [
        43.98,
        186.83,
        113.98,
        196.141
      ],
      "page_rect": [
        0.0,
        0.0,
        595.28,
        841.89
      ],
      "font_size": 7.0,
      "font": "MicrosoftJhengHeiRegular",
      "ascii_tokens": [],
      "cjk_char_count": 9,
      "preserve_tokens": [],
      "layout_hint": "short_label"
    },
    {
      "unit_id": "p4_b4_l69",
      "page_index": 4,
      "block_id": 4,
      "line_index": 69,
      "source_text": "香港上海滙豐銀⾏有限公司",
      "bbox": [
        43.98,
        196.58,
        127.98,
        205.891
      ],
      "page_rect": [
        0.0,
        0.0,
        595.28,
        841.89
      ],
      "font_size": 7.0,
      "font": "MicrosoftJhengHeiRegular",
      "ascii_tokens": [],
      "cjk_char_count": 11,
      "preserve_tokens": [],
      "layout_hint": "short_label"
    },
    {
      "unit_id": "p4_b4_l81",
      "page_index": 4,
      "block_id": 4,
      "line_index": 81,
      "source_text": "中東滙豐銀⾏有限公司",
      "bbox": [
        43.98,
        206.33,
        113.98,
        215.641
      ],
      "page_rect": [
        0.0,
        0.0,
        595.28,
        841.89
      ],
      "font_size": 7.0,
      "font": "MicrosoftJhengHeiRegular",
      "ascii_tokens": [],
      "cjk_char_count": 9,
      "preserve_tokens": [],
      "layout_hint": "short_label"
    },
    {
      "unit_id": "p4_b4_l93",
      "page_index": 4,
      "block_id": 4,
      "line_index": 93,
      "source_text": "北美滙豐控股有限公司",
      "bbox": [
        43.98,
        216.08,
        113.98,
        225.391
      ],
      "page_rect": [
        0.0,
        0.0,
        595.28,
        841.89
      ],
      "font_size": 7.0,
      "font": "MicrosoftJhengHeiRegular",
      "ascii_tokens": [],
      "cjk_char_count": 10,
      "preserve_tokens": [],
      "layout_hint": "short_label"
    },
    {
      "unit_id": "p4_b4_l117",
      "page_index": 4,
      "block_id": 4,
      "line_index": 117,
      "source_text": "其他交易實體",
      "bbox": [
        43.98,
        235.58,
        85.98,
        244.891
      ],
      "page_rect": [
        0.0,
        0.0,
        595.28,
        841.89
      ],
      "font_size": 7.0,
      "font": "MicrosoftJhengHeiRegular",
      "ascii_tokens": [],
      "cjk_char_count": 6,
      "preserve_tokens": [],
      "layout_hint": "short_label"
    },
    {
      "unit_id": "p4_b4_l129",
      "page_index": 4,
      "block_id": 4,
      "line_index": 129,
      "source_text": "於2025年6⽉30⽇",
      "bbox": [
        43.98,
        245.33,
        101.135,
        254.641
      ],
      "page_rect": [
        0.0,
        0.0,
        595.28,
        841.89
      ],
      "font_size": 7.0,
      "font": "MicrosoftJhengHeiBold",
      "ascii_tokens": [],
      "cjk_char_count": 2,
      "preserve_tokens": [
        {
          "type": "currency_amount",
          "value": "30"
        }
      ],
      "layout_hint": "short_label"
    },
    {
      "unit_id": "p4_b5_l0",
      "page_index": 4,
      "block_id": 5,
      "line_index": 0,
      "source_text": "企業及商業貸款",
      "bbox": [
        43.98,
        264.83,
        92.98,
        274.141
      ],
      "page_rect": [
        0.0,
        0.0,
        595.28,
        841.89
      ],
      "font_size": 7.0,
      "font": "MicrosoftJhengHeiRegular",
      "ascii_tokens": [],
      "cjk_char_count": 7,
      "preserve_tokens": [],
      "layout_hint": "short_label"
    },
    {
      "unit_id": "p4_b5_l10",
      "page_index": 4,
      "block_id": 5,
      "line_index": 10,
      "source_text": "⾦融機構",
      "bbox": [
        43.98,
        274.58,
        71.98,
        283.891
      ],
      "page_rect": [
        0.0,
        0.0,
        595.28,
        841.89
      ],
      "font_size": 7.0,
      "font": "MicrosoftJhengHeiRegular",
      "ascii_tokens": [],
      "cjk_char_count": 3,
      "preserve_tokens": [],
      "layout_hint": "short_label"
    },
    {
      "unit_id": "p4_b5_l20",
      "page_index": 4,
      "block_id": 5,
      "line_index": 20,
      "source_text": "於2024年12⽉31⽇",
      "bbox": [
        43.98,
        284.33,
        104.404,
        293.641
      ],
      "page_rect": [
        0.0,
        0.0,
        595.28,
        841.89
      ],
      "font_size": 7.0,
      "font": "MicrosoftJhengHeiRegular",
      "ascii_tokens": [],
      "cjk_char_count": 2,
      "preserve_tokens": [
        {
          "type": "currency_amount",
          "value": "31"
        }
      ],
      "layout_hint": "short_label"
    },
    {
      "unit_id": "p4_b5_l30",
      "page_index": 4,
      "block_id": 5,
      "line_index": 30,
      "source_text": "按法律實體列⽰",
      "bbox": [
        43.98,
        294.08,
        92.98,
        303.391
      ],
      "page_rect": [
        0.0,
        0.0,
        595.28,
        841.89
      ],
      "font_size": 7.0,
      "font": "MicrosoftJhengHeiRegular",
      "ascii_tokens": [],
      "cjk_char_count": 6,
      "preserve_tokens": [],
      "layout_hint": "short_label"
    },
    {
      "unit_id": "p4_b5_l43",
      "page_index": 4,
      "block_id": 5,
      "line_index": 43,
      "source_text": "英國滙豐銀⾏有限公司",
      "bbox": [
        43.98,
        313.58,
        113.98,
        322.891
      ],
      "page_rect": [
        0.0,
        0.0,
        595.28,
        841.89
      ],
      "font_size": 7.0,
      "font": "MicrosoftJhengHeiRegular",
      "ascii_tokens": [],
      "cjk_char_count": 9,
      "preserve_tokens": [],
      "layout_hint": "short_label"
    },
    {
      "unit_id": "p4_b5_l53",
      "page_index": 4,
      "block_id": 5,
      "line_index": 53,
      "source_text": "香港上海滙豐銀⾏有限公司",
      "bbox": [
        43.98,
        323.33,
        127.98,
        332.641
      ],
      "page_rect": [
        0.0,
        0.0,
        595.28,
        841.89
      ],
      "font_size": 7.0,
      "font": "MicrosoftJhengHeiRegular",
      "ascii_tokens": [],
      "cjk_char_count": 11,
      "preserve_tokens": [],
      "layout_hint": "short_label"
    },
    {
      "unit_id": "p4_b5_l65",
      "page_index": 4,
      "block_id": 5,
      "line_index": 65,
      "source_text": "中東滙豐銀⾏有限公司",
      "bbox": [
        43.98,
        333.08,
        113.98,
        342.391
      ],
      "page_rect": [
        0.0,
        0.0,
        595.28,
        841.89
      ],
      "font_size": 7.0,
      "font": "MicrosoftJhengHeiRegular",
      "ascii_tokens": [],
      "cjk_char_count": 9,
      "preserve_tokens": [],
      "layout_hint": "short_label"
    },
    {
      "unit_id": "p4_b5_l77",
      "page_index": 4,
      "block_id": 5,
      "line_index": 77,
      "source_text": "北美滙豐控股有限公司",
      "bbox": [
        43.98,
        342.83,
        113.98,
        352.141
      ],
      "page_rect": [
        0.0,
        0.0,
        595.28,
        841.89
      ],
      "font_size": 7.0,
      "font": "MicrosoftJhengHeiRegular",
      "ascii_tokens": [],
      "cjk_char_count": 10,
      "preserve_tokens": [],
      "layout_hint": "short_label"
    },
    {
      "unit_id": "p4_b5_l101",
      "page_index": 4,
      "block_id": 5,
      "line_index": 101,
      "source_text": "其他交易實體",
      "bbox": [
        43.98,
        362.33,
        85.98,
        371.641
      ],
      "page_rect": [
        0.0,
        0.0,
        595.28,
        841.89
      ],
      "font_size": 7.0,
      "font": "MicrosoftJhengHeiRegular",
      "ascii_tokens": [],
      "cjk_char_count": 6,
      "preserve_tokens": [],
      "layout_hint": "short_label"
    },
    {
      "unit_id": "p4_b5_l113",
      "page_index": 4,
      "block_id": 5,
      "line_index": 113,
      "source_text": "於2024年12⽉31⽇",
      "bbox": [
        43.98,
        372.08,
        104.404,
        381.391
      ],
      "page_rect": [
        0.0,
        0.0,
        595.28,
        841.89
      ],
      "font_size": 7.0,
      "font": "MicrosoftJhengHeiRegular",
      "ascii_tokens": [],
      "cjk_char_count": 2,
      "preserve_tokens": [
        {
          "type": "currency_amount",
          "value": "31"
        }
      ],
      "layout_hint": "short_label"
    },
    {
      "unit_id": "p4_b6_l0",
      "page_index": 4,
      "block_id": 6,
      "line_index": 0,
      "source_text": "1 與未結算反向回購協議相關之款額為950億美元（2024年12⽉31⽇：490億美元），計入貸款及其他信貸相關承諾以及財務擔保，相關款額⼀旦被取⽤，將分類為",
      "bbox": [
        41.35,
        388.57,
        550.432,
        397.881
      ],
      "page_rect": [
        0.0,
        0.0,
        595.28,
        841.89
      ],
      "font_size": 7.0,
      "font": "MicrosoftJhengHeiRegular",
      "ascii_tokens": [],
      "cjk_char_count": 53,
      "preserve_tokens": [
        {
          "type": "currency_amount",
          "value": "1 "
        },
        {
          "type": "currency_amount",
          "value": "31"
        }
      ],
      "layout_hint": "body"
    },
    {
      "unit_id": "p4_b6_l1",
      "page_index": 4,
      "block_id": 6,
      "line_index": 1,
      "source_text": "「反向回購協議 – 非交易⽤途」。",
      "bbox": [
        52.69,
        396.97,
        157.97,
        406.281
      ],
      "page_rect": [
        0.0,
        0.0,
        595.28,
        841.89
      ],
      "font_size": 7.0,
      "font": "MicrosoftJhengHeiRegular",
      "ascii_tokens": [],
      "cjk_char_count": 10,
      "preserve_tokens": [],
      "layout_hint": "short_label"
    },
    {
      "unit_id": "p4_b6_l2",
      "page_index": 4,
      "block_id": 6,
      "line_index": 2,
      "source_text": "2 第⼀級和第⼆級之間的「賬⾯總值」轉移（主要來⾃亞洲）是由於剩餘期限的平均違責或然率於業績報告⽇期增加，反映集團對違責或然率模型所作的更新及市場",
      "bbox": [
        41.35,
        405.37,
        549.69,
        414.681
      ],
      "page_rect": [
        0.0,
        0.0,
        595.28,
        841.89
      ],
      "font_size": 7.0,
      "font": "MicrosoftJhengHeiRegular",
      "ascii_tokens": [],
      "cjk_char_count": 61,
      "preserve_tokens": [
        {
          "type": "currency_amount",
          "value": "2 "
        }
      ],
      "layout_hint": "body"
    },
    {
      "unit_id": "p4_b6_l3",
      "page_index": 4,
      "block_id": 6,
      "line_index": 3,
      "source_text": "持續⾯對的挑戰。業績報告⽇期的違責或然率與承辦貸款時計算的違責或然率進⾏比較。",
      "bbox": [
        52.69,
        413.77,
        325.69,
        423.081
      ],
      "page_rect": [
        0.0,
        0.0,
        595.28,
        841.89
      ],
      "font_size": 7.0,
      "font": "MicrosoftJhengHeiRegular",
      "ascii_tokens": [],
      "cjk_char_count": 34,
      "preserve_tokens": [],
      "layout_hint": "body"
    },
    {
      "unit_id": "p4_b7_l0",
      "page_index": 4,
      "block_id": 7,
      "line_index": 0,
      "source_text": "商業房地產",
      "bbox": [
        41.35,
        427.371,
        111.35,
        445.992
      ],
      "page_rect": [
        0.0,
        0.0,
        595.28,
        841.89
      ],
      "font_size": 14.0,
      "font": "MicrosoftJhengHeiRegular",
      "ascii_tokens": [],
      "cjk_char_count": 5,
      "preserve_tokens": [],
      "layout_hint": "heading"
    },
    {
      "unit_id": "p4_b8_l0",
      "page_index": 4,
      "block_id": 8,
      "line_index": 0,
      "source_text": "商業房地產貸款包括為企業、機構和⾼淨值客⼾提供融資，這些客⼾主",
      "bbox": [
        41.35,
        446.285,
        289.35,
        456.925
      ],
      "page_rect": [
        0.0,
        0.0,
        595.28,
        841.89
      ],
      "font_size": 8.0,
      "font": "MicrosoftJhengHeiRegular",
      "ascii_tokens": [],
      "cjk_char_count": 26,
      "preserve_tokens": [],
      "layout_hint": "body"
    },
    {
      "unit_id": "p4_b8_l1",
      "page_index": 4,
      "block_id": 8,
      "line_index": 1,
      "source_text": "要投資於創收資產，其次投資於建設和開發。貸款組合分散在全球各",
      "bbox": [
        41.35,
        455.885,
        281.35,
        466.525
      ],
      "page_rect": [
        0.0,
        0.0,
        595.28,
        841.89
      ],
      "font_size": 8.0,
      "font": "MicrosoftJhengHeiRegular",
      "ascii_tokens": [],
      "cjk_char_count": 28,
      "preserve_tokens": [],
      "layout_hint": "body"
    }
  ],
  "terminology_policy": {
    "source": "current-run source units only",
    "known_reference_translation_allowed": false
  },
  "output_contract": {
    "workspace_boundary_ref": "docs/reports/round12/R12_00005_2025_interim_report_zh/translation_batches/batch_0010.workspace_boundary.json",
    "write_model_output_to": "docs/reports/round12/R12_00005_2025_interim_report_zh/translation_batches/batch_0010.model_output.json",
    "required_units": [
      "p4_b4_l2",
      "p4_b4_l3",
      "p4_b4_l4",
      "p4_b4_l5",
      "p4_b4_l6",
      "p4_b4_l7",
      "p4_b4_l8",
      "p4_b4_l9",
      "p4_b4_l10",
      "p4_b4_l11",
      "p4_b4_l12",
      "p4_b4_l13",
      "p4_b4_l14",
      "p4_b4_l15",
      "p4_b4_l25",
      "p4_b4_l35",
      "p4_b4_l46",
      "p4_b4_l59",
      "p4_b4_l69",
      "p4_b4_l81",
      "p4_b4_l93",
      "p4_b4_l117",
      "p4_b4_l129",
      "p4_b5_l0",
      "p4_b5_l10",
      "p4_b5_l20",
      "p4_b5_l30",
      "p4_b5_l43",
      "p4_b5_l53",
      "p4_b5_l65",
      "p4_b5_l77",
      "p4_b5_l101",
      "p4_b5_l113",
      "p4_b6_l0",
      "p4_b6_l1",
      "p4_b6_l2",
      "p4_b6_l3",
      "p4_b7_l0",
      "p4_b8_l0",
      "p4_b8_l1"
    ],
    "forbidden_placeholders": [
      "中文回填",
      "中文标题",
      "中文标签",
      "placeholder",
      "TBD"
    ]
  }
}