{
  "prompt_id": "D2_translation",
  "decision_contract": "D2_translation",
  "system_prompt": "You are a financial-report translation engine. Translate only supplied source units from source_language to target_language for the current batch. Preserve typed tokens such as years, percentages, currency amounts, dates, footnote markers, and table semantics. The target text must translate the actual source meaning, names, entities, relationships, and numeric claims. Neutral identifiers such as CUSIP, ISIN, SEDOL, RIC, LEI, ticker-like codes, rating letters, and uppercase alphanumeric security codes should normally be excluded by the batch manifest; if such a token appears inside a translated unit, preserve it as a neutral identifier instead of inventing a translation. Do not describe the line category, do not summarize as metadata, and do not emit boilerplate such as 'This line reports...', 'This line describes...', '本行说明...', '本行列示...', or '保留数值与标记...'. If a unit is a constrained label, compact label, legend, side navigation label, chart label, or table header, provide semantically tied shorter display variants in layout_variants; do not expect the PDF generator to invent abbreviations. Return strict JSON for this batch and do not omit units silently. If you cannot translate every unit in the batch, return FAIL and list missing_unit_ids; do not create placeholders.",
  "user_prompt": "Translate one D2 batch for run \"round15\" in state \"S5_TranslationPlan\". Run mode: \"product_quality\". Source PDF: \"docs/reports/round15/source_extraction_zh.json\". Source language: \"zh\". Target language: \"en\". Target text field: \"translation_en\". Batch id: \"batch_0086\". Batch index/count: 86/166. Batch slot values ref: \"docs/reports/round15/translation_batches/batch_0086.slot_values.json\". Translation units: [{\"unit_id\": \"p171_b18_l2\", \"page_index\": 171, \"block_id\": 18, \"line_index\": 2, \"source_text\": \"浪持續）。\", \"bbox\": [173.37, 358.11, 208.37, 367.421], \"page_rect\": [0.0, 0.0, 595.28, 841.89], \"font_size\": 7.0, \"font\": \"MicrosoftJhengHeiRegular\", \"ascii_tokens\": [], \"cjk_char_count\": 3, \"preserve_tokens\": [], \"layout_hint\": \"short_label\"}, {\"unit_id\": \"p171_b19_l0\", \"page_index\": 171, \"block_id\": 19, \"line_index\": 0, \"source_text\": \"過渡\", \"bbox\": [45.12, 369.96, 59.12, 379.271], \"page_rect\": [0.0, 0.0, 595.28, 841.89], \"font_size\": 7.0, \"font\": \"MicrosoftJhengHeiBold\", \"ascii_tokens\": [], \"cjk_char_count\": 2, \"preserve_tokens\": [], \"layout_hint\": \"short_label\"}, {\"unit_id\": \"p171_b19_l1\", \"page_index\": 171, \"block_id\": 19, \"line_index\": 1, \"source_text\": \"政策及法律\", \"bbox\": [106.62, 369.96, 141.62, 379.271], \"page_rect\": [0.0, 0.0, 595.28, 841.89], \"font_size\": 7.0, \"font\": \"MicrosoftJhengHeiBold\", \"ascii_tokens\": [], \"cjk_char_count\": 5, \"preserve_tokens\": [], \"layout_hint\": \"short_label\"}, {\"unit_id\": \"p171_b19_l2\", \"page_index\": 171, \"block_id\": 19, \"line_index\": 2, \"source_text\": \"有關產品及服務的授權和規管及／或對低碳替代選擇的政策⽀持。因\", \"bbox\": [173.37, 369.96, 383.37, 379.271], \"page_rect\": [0.0, 0.0, 595.28, 841.89], \"font_size\": 7.0, \"font\": \"MicrosoftJhengHeiRegular\", \"ascii_tokens\": [], \"cjk_char_count\": 27, \"preserve_tokens\": [], \"layout_hint\": \"body\"}, {\"unit_id\": \"p171_b19_l3\", \"page_index\": 171, \"block_id\": 19, \"line_index\": 3, \"source_text\": \"氣候影響蒙受損失及損害者提起訴訟。\", \"bbox\": [173.37, 378.36, 292.37, 387.671], \"page_rect\": [0.0, 0.0, 595.28, 841.89], \"font_size\": 7.0, \"font\": \"MicrosoftJhengHeiRegular\", \"ascii_tokens\": [], \"cjk_char_count\": 16, \"preserve_tokens\": [], \"layout_hint\": \"short_label\"}, {\"unit_id\": \"p171_b20_l0\", \"page_index\": 171, \"block_id\": 20, \"line_index\": 0, \"source_text\": \"科技\", \"bbox\": [106.62, 390.21, 120.62, 399.521], \"page_rect\": [0.0, 0.0, 595.28, 841.89], \"font_size\": 7.0, \"font\": \"MicrosoftJhengHeiBold\", \"ascii_tokens\": [], \"cjk_char_count\": 2, \"preserve_tokens\": [], \"layout_hint\": \"short_label\"}, {\"unit_id\": \"p171_b20_l1\", \"page_index\": 171, \"block_id\": 20, \"line_index\": 1, \"source_text\": \"現有產品被排放較少的產品取代。\", \"bbox\": [173.37, 390.21, 278.37, 399.521], \"page_rect\": [0.0, 0.0, 595.28, 841.89], \"font_size\": 7.0, \"font\": \"MicrosoftJhengHeiRegular\", \"ascii_tokens\": [], \"cjk_char_count\": 14, \"preserve_tokens\": [], \"layout_hint\": \"short_label\"}, {\"unit_id\": \"p171_b21_l0\", \"page_index\": 171, \"block_id\": 21, \"line_index\": 0, \"source_text\": \"終端需求（市場）\", \"bbox\": [106.62, 401.46, 162.62, 410.771], \"page_rect\": [0.0, 0.0, 595.28, 841.89], \"font_size\": 7.0, \"font\": \"MicrosoftJhengHeiBold\", \"ascii_tokens\": [], \"cjk_char_count\": 6, \"preserve_tokens\": [], \"layout_hint\": \"short_label\"}, {\"unit_id\": \"p171_b21_l1\", \"page_index\": 171, \"block_id\": 21, \"line_index\": 1, \"source_text\": \"個⼈及企業消費者需求轉變。\", \"bbox\": [173.37, 401.46, 264.37, 410.771], \"page_rect\": [0.0, 0.0, 595.28, 841.89], \"font_size\": 7.0, \"font\": \"MicrosoftJhengHeiRegular\", \"ascii_tokens\": [], \"cjk_char_count\": 11, \"preserve_tokens\": [], \"layout_hint\": \"short_label\"}, {\"unit_id\": \"p171_b22_l0\", \"page_index\": 171, \"block_id\": 22, \"line_index\": 0, \"source_text\": \"聲譽\", \"bbox\": [106.62, 412.71, 120.62, 422.021], \"page_rect\": [0.0, 0.0, 595.28, 841.89], \"font_size\": 7.0, \"font\": \"MicrosoftJhengHeiBold\", \"ascii_tokens\": [], \"cjk_char_count\": 2, \"preserve_tokens\": [], \"layout_hint\": \"short_label\"}, {\"unit_id\": \"p171_b22_l1\", \"page_index\": 171, \"block_id\": 22, \"line_index\": 1, \"source_text\": \"相關群體對於有否採取氣候相關⾏動的觀感有變，加上各種國家和政\", \"bbox\": [173.37, 412.71, 383.37, 422.021], \"page_rect\": [0.0, 0.0, 595.28, 841.89], \"font_size\": 7.0, \"font\": \"MicrosoftJhengHeiRegular\", \"ascii_tokens\": [], \"cjk_char_count\": 28, \"preserve_tokens\": [], \"layout_hint\": \"body\"}, {\"unit_id\": \"p171_b22_l2\", \"page_index\": 171, \"block_id\": 22, \"line_index\": 2, \"source_text\": \"治考量，導致監察更加嚴謹。\", \"bbox\": [173.37, 421.11, 264.37, 430.421], \"page_rect\": [0.0, 0.0, 595.28, 841.89], \"font_size\": 7.0, \"font\": \"MicrosoftJhengHeiRegular\", \"ascii_tokens\": [], \"cjk_char_count\": 11, \"preserve_tokens\": [], \"layout_hint\": \"short_label\"}, {\"unit_id\": \"p171_b23_l0\", \"page_index\": 171, \"block_id\": 23, \"line_index\": 0, \"source_text\": \"氣候風險 – 主題風險議題\", \"bbox\": [42.73, 443.775, 131.05, 454.415], \"page_rect\": [0.0, 0.0, 595.28, 841.89], \"font_size\": 8.0, \"font\": \"MicrosoftJhengHeiRegular\", \"ascii_tokens\": [], \"cjk_char_count\": 10, \"preserve_tokens\": [], \"layout_hint\": \"short_label\"}, {\"unit_id\": \"p171_b24_l0\", \"page_index\": 171, \"block_id\": 24, \"line_index\": 0, \"source_text\": \"漂綠風險\", \"bbox\": [45.0, 456.71, 73.0, 466.021], \"page_rect\": [0.0, 0.0, 595.28, 841.89], \"font_size\": 7.0, \"font\": \"MicrosoftJhengHeiBold\", \"ascii_tokens\": [], \"cjk_char_count\": 4, \"preserve_tokens\": [], \"layout_hint\": \"short_label\"}, {\"unit_id\": \"p171_b24_l1\", \"page_index\": 171, \"block_id\": 24, \"line_index\": 1, \"source_text\": \"公司\", \"bbox\": [107.25, 456.84, 121.25, 466.151], \"page_rect\": [0.0, 0.0, 595.28, 841.89], \"font_size\": 7.0, \"font\": \"MicrosoftJhengHeiBold\", \"ascii_tokens\": [], \"cjk_char_count\": 2, \"preserve_tokens\": [], \"layout_hint\": \"short_label\"}, {\"unit_id\": \"p171_b24_l2\", \"page_index\": 171, \"block_id\": 24, \"line_index\": 2, \"source_text\": \"就我們的可持續發展抱負、⽬標與承諾，以及在相關表現報告中，作出不準確、不清晰、具誤導成分或未經證實的聲稱。\", \"bbox\": [174.0, 456.84, 545.0, 466.151], \"page_rect\": [0.0, 0.0, 595.28, 841.89], \"font_size\": 7.0, \"font\": \"MicrosoftJhengHeiRegular\", \"ascii_tokens\": [], \"cjk_char_count\": 46, \"preserve_tokens\": [], \"layout_hint\": \"body\"}, {\"unit_id\": \"p171_b25_l0\", \"page_index\": 171, \"block_id\": 25, \"line_index\": 0, \"source_text\": \"產品\", \"bbox\": [107.25, 467.96, 121.25, 477.271], \"page_rect\": [0.0, 0.0, 595.28, 841.89], \"font_size\": 7.0, \"font\": \"MicrosoftJhengHeiBold\", \"ascii_tokens\": [], \"cjk_char_count\": 2, \"preserve_tokens\": [], \"layout_hint\": \"short_label\"}, {\"unit_id\": \"p171_b25_l1\", \"page_index\": 171, \"block_id\": 25, \"line_index\": 1, \"source_text\": \"就我們向客⼾提供且列明具可持續發展⽬標、特點、影響或特⾊的產品或服務，作出不準確、不清晰、具誤導成分或未經\", \"bbox\": [174.0, 467.96, 545.0, 477.271], \"page_rect\": [0.0, 0.0, 595.28, 841.89], \"font_size\": 7.0, \"font\": \"MicrosoftJhengHeiRegular\", \"ascii_tokens\": [], \"cjk_char_count\": 45, \"preserve_tokens\": [], \"layout_hint\": \"body\"}, {\"unit_id\": \"p171_b25_l2\", \"page_index\": 171, \"block_id\": 25, \"line_index\": 2, \"source_text\": \"證實的聲稱。\", \"bbox\": [174.0, 476.36, 216.0, 485.671], \"page_rect\": [0.0, 0.0, 595.28, 841.89], \"font_size\": 7.0, \"font\": \"MicrosoftJhengHeiRegular\", \"ascii_tokens\": [], \"cjk_char_count\": 5, \"preserve_tokens\": [], \"layout_hint\": \"short_label\"}, {\"unit_id\": \"p171_b26_l0\", \"page_index\": 171, \"block_id\": 26, \"line_index\": 0, \"source_text\": \"客⼾\", \"bbox\": [107.25, 488.21, 121.25, 497.521], \"page_rect\": [0.0, 0.0, 595.28, 841.89], \"font_size\": 7.0, \"font\": \"MicrosoftJhengHeiBold\", \"ascii_tokens\": [], \"cjk_char_count\": 1, \"preserve_tokens\": [], \"layout_hint\": \"short_label\"}, {\"unit_id\": \"p171_b26_l1\", \"page_index\": 171, \"block_id\": 26, \"line_index\": 1, \"source_text\": \"由於客⼾的可持續發展承諾或相關表現存在失實陳述或與我們本⾝的承諾不符，導致我們因與該等客⼾的關係或交易作出\", \"bbox\": [174.0, 488.21, 545.0, 497.521], \"page_rect\": [0.0, 0.0, 595.28, 841.89], \"font_size\": 7.0, \"font\": \"MicrosoftJhengHeiRegular\", \"ascii_tokens\": [], \"cjk_char_count\": 49, \"preserve_tokens\": [], \"layout_hint\": \"body\"}, {\"unit_id\": \"p171_b26_l2\", \"page_index\": 171, \"block_id\": 26, \"line_index\": 2, \"source_text\": \"不準確、不清晰、具誤導成分或未經證實的聲稱。\", \"bbox\": [174.0, 496.61, 328.0, 505.921], \"page_rect\": [0.0, 0.0, 595.28, 841.89], \"font_size\": 7.0, \"font\": \"MicrosoftJhengHeiRegular\", \"ascii_tokens\": [], \"cjk_char_count\": 19, \"preserve_tokens\": [], \"layout_hint\": \"short_label\"}, {\"unit_id\": \"p171_b27_l0\", \"page_index\": 171, \"block_id\": 27, \"line_index\": 0, \"source_text\": \"我們的年度氣候風險重要性評估，有助我們了解氣候風險如何影響滙豐\", \"bbox\": [42.37, 517.145, 287.97, 527.785], \"page_rect\": [0.0, 0.0, 595.28, 841.89], \"font_size\": 8.0, \"font\": \"MicrosoftJhengHeiRegular\", \"ascii_tokens\": [], \"cjk_char_count\": 30, \"preserve_tokens\": [], \"layout_hint\": \"body\"}, {\"unit_id\": \"p171_b27_l1\", \"page_index\": 171, \"block_id\": 27, \"line_index\": 1, \"source_text\": \"的風險類別。此項評估考慮12個⽉期間的影響類別、可能性及嚴重程\", \"bbox\": [42.37, 526.745, 281.234, 537.385], \"page_rect\": [0.0, 0.0, 595.28, 841.89], \"font_size\": 8.0, \"font\": \"MicrosoftJhengHeiRegular\", \"ascii_tokens\": [], \"cjk_char_count\": 26, \"preserve_tokens\": [], \"layout_hint\": \"body\"}, {\"unit_id\": \"p171_b27_l2\", \"page_index\": 171, \"block_id\": 27, \"line_index\": 2, \"source_text\": \"度，並且考慮前瞻性風險影響。\", \"bbox\": [42.37, 536.345, 153.33, 546.985], \"page_rect\": [0.0, 0.0, 595.28, 841.89], \"font_size\": 8.0, \"font\": \"MicrosoftJhengHeiRegular\", \"ascii_tokens\": [], \"cjk_char_count\": 12, \"preserve_tokens\": [], \"layout_hint\": \"short_label\"}, {\"unit_id\": \"p171_b28_l0\", \"page_index\": 171, \"block_id\": 28, \"line_index\": 0, \"source_text\": \"我們亦運⽤有關評估協助制訂政策、提升管控措施及境況分析。有關⽤\", \"bbox\": [304.57, 517.145, 550.17, 527.785], \"page_rect\": [0.0, 0.0, 595.28, 841.89], \"font_size\": 8.0, \"font\": \"MicrosoftJhengHeiRegular\", \"ascii_tokens\": [], \"cjk_char_count\": 27, \"preserve_tokens\": [], \"layout_hint\": \"body\"}, {\"unit_id\": \"p171_b28_l1\", \"page_index\": 171, \"block_id\": 28, \"line_index\": 1, \"source_text\": \"作評估潛在風險的境況分析及時間範圍定義的詳情，請參閱第173⾴。\", \"bbox\": [304.57, 526.745, 547.986, 537.385], \"page_rect\": [0.0, 0.0, 595.28, 841.89], \"font_size\": 8.0, \"font\": \"MicrosoftJhengHeiRegular\", \"ascii_tokens\": [], \"cjk_char_count\": 26, \"preserve_tokens\": [], \"layout_hint\": \"body\"}, {\"unit_id\": \"p171_b29_l0\", \"page_index\": 171, \"block_id\": 29, \"line_index\": 0, \"source_text\": \"氣候風險催化因素\", \"bbox\": [45.0, 569.89, 101.0, 579.201], \"page_rect\": [0.0, 0.0, 595.28, 841.89], \"font_size\": 7.0, \"font\": \"MicrosoftJhengHeiBold\", \"ascii_tokens\": [], \"cjk_char_count\": 8, \"preserve_tokens\": [], \"layout_hint\": \"short_label\"}, {\"unit_id\": \"p171_b29_l1\", \"page_index\": 171, \"block_id\": 29, \"line_index\": 1, \"source_text\": \"信貸風險\", \"bbox\": [181.37, 569.89, 209.37, 579.201], \"page_rect\": [0.0, 0.0, 595.28, 841.89], \"font_size\": 7.0, \"font\": \"MicrosoftJhengHeiBold\", \"ascii_tokens\": [], \"cjk_char_count\": 4, \"preserve_tokens\": [], \"layout_hint\": \"short_label\"}, {\"unit_id\": \"p171_b29_l2\", \"page_index\": 171, \"block_id\": 29, \"line_index\": 2, \"source_text\": \"交易風險\", \"bbox\": [241.37, 569.89, 269.37, 579.201], \"page_rect\": [0.0, 0.0, 595.28, 841.89], \"font_size\": 7.0, \"font\": \"MicrosoftJhengHeiBold\", \"ascii_tokens\": [], \"cjk_char_count\": 4, \"preserve_tokens\": [], \"layout_hint\": \"short_label\"}, {\"unit_id\": \"p171_b29_l3\", \"page_index\": 171, \"block_id\": 29, \"line_index\": 3, \"source_text\": \"聲譽風險\", \"bbox\": [306.99, 569.89, 334.99, 579.201], \"page_rect\": [0.0, 0.0, 595.28, 841.89], \"font_size\": 7.0, \"font\": \"MicrosoftJhengHeiBold\", \"ascii_tokens\": [], \"cjk_char_count\": 4, \"preserve_tokens\": [], \"layout_hint\": \"short_label\"}, {\"unit_id\": \"p171_b29_l4\", \"page_index\": 171, \"block_id\": 29, \"line_index\": 4, \"source_text\": \"監管合規風險\", \"bbox\": [368.24, 569.89, 410.24, 579.201], \"page_rect\": [0.0, 0.0, 595.28, 841.89], \"font_size\": 7.0, \"font\": \"MicrosoftJhengHeiBold\", \"ascii_tokens\": [], \"cjk_char_count\": 6, \"preserve_tokens\": [], \"layout_hint\": \"short_label\"}, {\"unit_id\": \"p171_b29_l5\", \"page_index\": 171, \"block_id\": 29, \"line_index\": 5, \"source_text\": \"復元⼒風險\", \"bbox\": [436.99, 569.89, 471.99, 579.201], \"page_rect\": [0.0, 0.0, 595.28, 841.89], \"font_size\": 7.0, \"font\": \"MicrosoftJhengHeiBold\", \"ascii_tokens\": [], \"cjk_char_count\": 4, \"preserve_tokens\": [], \"layout_hint\": \"short_label\"}, {\"unit_id\": \"p171_b30_l0\", \"page_index\": 171, \"block_id\": 30, \"line_index\": 0, \"source_text\": \"其他財務及\", \"bbox\": [502.24, 561.49, 537.24, 570.801], \"page_rect\": [0.0, 0.0, 595.28, 841.89], \"font_size\": 7.0, \"font\": \"MicrosoftJhengHeiBold\", \"ascii_tokens\": [], \"cjk_char_count\": 5, \"preserve_tokens\": [], \"layout_hint\": \"short_label\"}, {\"unit_id\": \"p171_b30_l1\", \"page_index\": 171, \"block_id\": 30, \"line_index\": 1, \"source_text\": \"非財務風險類別\", \"bbox\": [495.24, 569.89, 544.24, 579.201], \"page_rect\": [0.0, 0.0, 595.28, 841.89], \"font_size\": 7.0, \"font\": \"MicrosoftJhengHeiBold\", \"ascii_tokens\": [], \"cjk_char_count\": 7, \"preserve_tokens\": [], \"layout_hint\": \"short_label\"}, {\"unit_id\": \"p171_b31_l0\", \"page_index\": 171, \"block_id\": 31, \"line_index\": 0, \"source_text\": \"實體風險\", \"bbox\": [45.0, 581.07, 73.0, 590.381], \"page_rect\": [0.0, 0.0, 595.28, 841.89], \"font_size\": 7.0, \"font\": \"MicrosoftJhengHeiBold\", \"ascii_tokens\": [], \"cjk_char_count\": 4, \"preserve_tokens\": [], \"layout_hint\": \"short_label\"}, {\"unit_id\": \"p171_b32_l0\", \"page_index\": 171, \"block_id\": 32, \"line_index\": 0, \"source_text\": \"過渡風險\", \"bbox\": [45.0, 592.26, 73.0, 601.571], \"page_rect\": [0.0, 0.0, 595.28, 841.89], \"font_size\": 7.0, \"font\": \"MicrosoftJhengHeiBold\", \"ascii_tokens\": [], \"cjk_char_count\": 4, \"preserve_tokens\": [], \"layout_hint\": \"short_label\"}, {\"unit_id\": \"p171_b33_l0\", \"page_index\": 171, \"block_id\": 33, \"line_index\": 0, \"source_text\": \"策略報告\", \"bbox\": [45.0, 15.84, 73.0, 25.151], \"page_rect\": [0.0, 0.0, 595.28, 841.89], \"font_size\": 7.0, \"font\": \"MicrosoftJhengHeiRegular\", \"ascii_tokens\": [], \"cjk_char_count\": 4, \"preserve_tokens\": [], \"layout_hint\": \"short_label\"}, {\"unit_id\": \"p171_b33_l1\", \"page_index\": 171, \"block_id\": 33, \"line_index\": 1, \"source_text\": \"環境、社會及\", \"bbox\": [118.5, 15.84, 160.5, 25.151], \"page_rect\": [0.0, 0.0, 595.28, 841.89], \"font_size\": 7.0, \"font\": \"MicrosoftJhengHeiRegular\", \"ascii_tokens\": [], \"cjk_char_count\": 5, \"preserve_tokens\": [], \"layout_hint\": \"short_label\"}, {\"unit_id\": \"p171_b33_l2\", \"page_index\": 171, \"block_id\": 33, \"line_index\": 2, \"source_text\": \"管治報告\", \"bbox\": [118.5, 24.24, 146.5, 33.551], \"page_rect\": [0.0, 0.0, 595.28, 841.89], \"font_size\": 7.0, \"font\": \"MicrosoftJhengHeiRegular\", \"ascii_tokens\": [], \"cjk_char_count\": 4, \"preserve_tokens\": [], \"layout_hint\": \"short_label\"}, {\"unit_id\": \"p171_b33_l3\", \"page_index\": 171, \"block_id\": 33, \"line_index\": 3, \"source_text\": \"財務回顧\", \"bbox\": [192.0, 15.84, 220.0, 25.151], \"page_rect\": [0.0, 0.0, 595.28, 841.89], \"font_size\": 7.0, \"font\": \"MicrosoftJhengHeiRegular\", \"ascii_tokens\": [], \"cjk_char_count\": 4, \"preserve_tokens\": [], \"layout_hint\": \"short_label\"}, {\"unit_id\": \"p171_b33_l4\", \"page_index\": 171, \"block_id\": 33, \"line_index\": 4, \"source_text\": \"風險回顧\", \"bbox\": [265.5, 15.84, 293.5, 25.151], \"page_rect\": [0.0, 0.0, 595.28, 841.89], \"font_size\": 7.0, \"font\": \"MicrosoftJhengHeiBold\", \"ascii_tokens\": [], \"cjk_char_count\": 4, \"preserve_tokens\": [], \"layout_hint\": \"short_label\"}, {\"unit_id\": \"p171_b33_l5\", \"page_index\": 171, \"block_id\": 33, \"line_index\": 5, \"source_text\": \"企業管治報告\", \"bbox\": [339.0, 15.84, 379.565, 25.151], \"page_rect\": [0.0, 0.0, 595.28, 841.89], \"font_size\": 7.0, \"font\": \"MicrosoftJhengHeiRegular\", \"ascii_tokens\": [], \"cjk_char_count\": 6, \"preserve_tokens\": [], \"layout_hint\": \"short_label\"}, {\"unit_id\": \"p171_b33_l6\", \"page_index\": 171, \"block_id\": 33, \"line_index\": 6, \"source_text\": \"財務報表\", \"bbox\": [412.5, 15.84, 440.5, 25.151], \"page_rect\": [0.0, 0.0, 595.28, 841.89], \"font_size\": 7.0, \"font\": \"MicrosoftJhengHeiRegular\", \"ascii_tokens\": [], \"cjk_char_count\": 4, \"preserve_tokens\": [], \"layout_hint\": \"short_label\"}, {\"unit_id\": \"p171_b33_l7\", \"page_index\": 171, \"block_id\": 33, \"line_index\": 7, \"source_text\": \"補充資料\", \"bbox\": [486.0, 15.84, 514.0, 25.151], \"page_rect\": [0.0, 0.0, 595.28, 841.89], \"font_size\": 7.0, \"font\": \"MicrosoftJhengHeiRegular\", \"ascii_tokens\": [], \"cjk_char_count\": 4, \"preserve_tokens\": [], \"layout_hint\": \"short_label\"}, {\"unit_id\": \"p171_b34_l0\", \"page_index\": 171, \"block_id\": 34, \"line_index\": 0, \"source_text\": \"滙豐控股有限公司 2025年報及賬⽬\", \"bbox\": [244.02, 808.67, 352.982, 817.981], \"page_rect\": [0.0, 0.0, 595.28, 841.89], \"font_size\": 7.0, \"font\": \"MicrosoftJhengHeiBold\", \"ascii_tokens\": [], \"cjk_char_count\": 12, \"preserve_tokens\": [], \"layout_hint\": \"short_label\"}, {\"unit_id\": \"p172_b0_l0\", \"page_index\": 172, \"block_id\": 0, \"line_index\": 0, \"source_text\": \"氣候風險管理\", \"bbox\": [42.37, 68.531, 126.37, 87.152], \"page_rect\": [0.0, 0.0, 595.28, 841.89], \"font_size\": 14.0, \"font\": \"MicrosoftJhengHeiRegular\", \"ascii_tokens\": [], \"cjk_char_count\": 6, \"preserve_tokens\": [], \"layout_hint\": \"heading\"}, {\"unit_id\": \"p172_b1_l0\", \"page_index\": 172, \"block_id\": 1, \"line_index\": 0, \"source_text\": \"2025年主要發展\", \"bbox\": [42.37, 89.516, 137.49, 106.807], \"page_rect\": [0.0, 0.0, 595.28, 841.89], \"font_size\": 13.0, \"font\": \"MicrosoftJhengHeiRegular\", \"ascii_tokens\": [], \"cjk_char_count\": 5, \"preserve_tokens\": [], \"layout_hint\": \"short_label\"}, {\"unit_id\": \"p172_b2_l0\", \"page_index\": 172, \"block_id\": 2, \"line_index\": 0, \"source_text\": \"我們繼續發展氣候風險管理能⼒。2025年的主要發展載列如下：\", \"bbox\": [42.37, 107.045, 266.578, 117.685], \"page_rect\": [0.0, 0.0, 595.28, 841.89], \"font_size\": 8.0, \"font\": \"MicrosoftJhengHeiRegular\", \"ascii_tokens\": [], \"cjk_char_count\": 23, \"preserve_tokens\": [], \"layout_hint\": \"body\"}, {\"unit_id\": \"p172_b3_l1\", \"page_index\": 172, \"block_id\": 3, \"line_index\": 1, \"source_text\": \"我們透過發展貸款組合督導能⼒及制訂風險收益評估，加強集團管\", \"bbox\": [53.71, 123.145, 283.47, 133.785], \"page_rect\": [0.0, 0.0, 595.28, 841.89], \"font_size\": 8.0, \"font\": \"MicrosoftJhengHeiRegular\", \"ascii_tokens\": [], \"cjk_char_count\": 27, \"preserve_tokens\": [], \"layout_hint\": \"body\"}, {\"unit_id\": \"p172_b3_l2\", \"page_index\": 172, \"block_id\": 3, \"line_index\": 2, \"source_text\": \"理批發貸款組合融資項⽬排放⽬標的⽅針。\", \"bbox\": [53.71, 132.745, 204.27, 143.385], \"page_rect\": [0.0, 0.0, 595.28, 841.89], \"font_size\": 8.0, \"font\": \"MicrosoftJhengHeiRegular\", \"ascii_tokens\": [], \"cjk_char_count\": 15, \"preserve_tokens\": [], \"layout_hint\": \"short_label\"}, {\"unit_id\": \"p172_b3_l4\", \"page_index\": 172, \"block_id\": 3, \"line_index\": 4, \"source_text\": \"我們以信貸、交易及營運風險為重點，加強集團評估氣候變化對資\", \"bbox\": [53.71, 144.345, 283.47, 154.985], \"page_rect\": [0.0, 0.0, 595.28, 841.89], \"font_size\": 8.0, \"font\": \"MicrosoftJhengHeiRegular\", \"ascii_tokens\": [], \"cjk_char_count\": 27, \"preserve_tokens\": [], \"layout_hint\": \"body\"}, {\"unit_id\": \"p172_b3_l5\", \"page_index\": 172, \"block_id\": 3, \"line_index\": 5, \"source_text\": \"本影響的⽅針。\", \"bbox\": [53.71, 153.944, 109.23, 164.585], \"page_rect\": [0.0, 0.0, 595.28, 841.89], \"font_size\": 8.0, \"font\": \"MicrosoftJhengHeiRegular\", \"ascii_tokens\": [], \"cjk_char_count\": 5, \"preserve_tokens\": [], \"layout_hint\": \"short_label\"}, {\"unit_id\": \"p172_b3_l7\", \"page_index\": 172, \"block_id\": 3, \"line_index\": 7, \"source_text\": \"我們加強集團內部氣候境況分析，包括改進輸入的數據及模型。有\", \"bbox\": [53.71, 165.544, 283.47, 176.185], \"page_rect\": [0.0, 0.0, 595.28, 841.89], \"font_size\": 8.0, \"font\": \"MicrosoftJhengHeiRegular\", \"ascii_tokens\": [], \"cjk_char_count\": 27, \"preserve_tokens\": [], \"layout_hint\": \"body\"}, {\"unit_id\": \"p172_b3_l8\", \"page_index\": 172, \"block_id\": 3, \"line_index\": 8, \"source_text\": \"關境況分析詳情，請參閱第173⾴。\", \"bbox\": [53.71, 175.144, 178.326, 185.785], \"page_rect\": [0.0, 0.0, 595.28, 841.89], \"font_size\": 8.0, \"font\": \"MicrosoftJhengHeiRegular\", \"ascii_tokens\": [], \"cjk_char_count\": 11, \"preserve_tokens\": [], \"layout_hint\": \"short_label\"}, {\"unit_id\": \"p172_b3_l10\", \"page_index\": 172, \"block_id\": 3, \"line_index\": 10, \"source_text\": \"我們加強集團管理及緩減漂綠風險的⽅針。\", \"bbox\": [53.71, 186.744, 204.27, 197.385], \"page_rect\": [0.0, 0.0, 595.28, 841.89], \"font_size\": 8.0, \"font\": \"MicrosoftJhengHeiRegular\", \"ascii_tokens\": [], \"cjk_char_count\": 17, \"preserve_tokens\": [], \"layout_hint\": \"short_label\"}, {\"unit_id\": \"p172_b3_l12\", \"page_index\": 172, \"block_id\": 3, \"line_index\": 12, \"source_text\": \"我們為客⼾經理修訂氣候風險管理指引，藉以在信貸風險評估過程\", \"bbox\": [53.71, 198.344, 283.47, 208.985], \"page_rect\": [0.0, 0.0, 595.28, 841.89], \"font_size\": 8.0, \"font\": \"MicrosoftJhengHeiRegular\", \"ascii_tokens\": [], \"cjk_char_count\": 27, \"preserve_tokens\": [], \"layout_hint\": \"body\"}, {\"unit_id\": \"p172_b3_l13\", \"page_index\": 172, \"block_id\": 3, \"line_index\": 13, \"source_text\": \"中進⼀步包含氣候風險考慮因素。\", \"bbox\": [53.71, 207.944, 172.59, 218.585], \"page_rect\": [0.0, 0.0, 595.28, 841.89], \"font_size\": 8.0, \"font\": \"MicrosoftJhengHeiRegular\", \"ascii_tokens\": [], \"cjk_char_count\": 13, \"preserve_tokens\": [], \"layout_hint\": \"short_label\"}, {\"unit_id\": \"p172_b4_l0\", \"page_index\": 172, \"block_id\": 4, \"line_index\": 0, \"source_text\": \"儘管集團在各⽅⾯取得進展，但仍有更多⼯作需要完成，包括需要進⼀\", \"bbox\": [42.37, 224.044, 287.97, 234.685], \"page_rect\": [0.0, 0.0, 595.28, 841.89], \"font_size\": 8.0, \"font\": \"MicrosoftJhengHeiRegular\", \"ascii_tokens\": [], \"cjk_char_count\": 25, \"preserve_tokens\": [], \"layout_hint\": \"body\"}, {\"unit_id\": \"p172_b4_l1\", \"page_index\": 172, \"block_id\": 4, \"line_index\": 1, \"source_text\": \"步發展其他計量集團所涉氣候相關風險承擔的衡量指標及⼯具。\", \"bbox\": [42.37, 233.644, 264.21, 244.285], \"page_rect\": [0.0, 0.0, 595.28, 841.89], \"font_size\": 8.0, \"font\": \"MicrosoftJhengHeiRegular\", \"ascii_tokens\": [], \"cjk_char_count\": 26, \"preserve_tokens\": [], \"layout_hint\": \"body\"}, {\"unit_id\": \"p172_b5_l0\", \"page_index\": 172, \"block_id\": 5, \"line_index\": 0, \"source_text\": \"管治及架構\", \"bbox\": [42.37, 248.816, 107.37, 266.107], \"page_rect\": [0.0, 0.0, 595.28, 841.89], \"font_size\": 13.0, \"font\": \"MicrosoftJhengHeiRegular\", \"ascii_tokens\": [], \"cjk_char_count\": 5, \"preserve_tokens\": [], \"layout_hint\": \"short_label\"}, {\"unit_id\": \"p172_b6_l0\", \"page_index\": 172, \"block_id\": 6, \"line_index\": 0, \"source_text\": \"董事會就集團的環境、社會及管治策略承擔整體監督責任，負責監督制\", \"bbox\": [42.37, 266.344, 287.97, 276.985], \"page_rect\": [0.0, 0.0, 595.28, 841.89], \"font_size\": 8.0, \"font\": \"MicrosoftJhengHeiRegular\", \"ascii_tokens\": [], \"cjk_char_count\": 29, \"preserve_tokens\": [], \"layout_hint\": \"body\"}, {\"unit_id\": \"p172_b6_l1\", \"page_index\": 172, \"block_id\": 6, \"line_index\": 1, \"source_text\": \"訂⽅針、執⾏及相關報告的⾏政管理。\", \"bbox\": [42.37, 275.944, 177.09, 286.585], \"page_rect\": [0.0, 0.0, 595.28, 841.89], \"font_size\": 8.0, \"font\": \"MicrosoftJhengHeiRegular\", \"ascii_tokens\": [], \"cjk_char_count\": 12, \"preserve_tokens\": [], \"layout_hint\": \"short_label\"}, {\"unit_id\": \"p172_b7_l0\", \"page_index\": 172, \"block_id\": 7, \"line_index\": 0, \"source_text\": \"集團風險管理與合規總監為英國⾼級管理⼈員制度下負責管理氣候風險\", \"bbox\": [42.37, 292.044, 287.97, 302.685], \"page_rect\": [0.0, 0.0, 595.28, 841.89], \"font_size\": 8.0, \"font\": \"MicrosoftJhengHeiRegular\", \"ascii_tokens\": [], \"cjk_char_count\": 29, \"preserve_tokens\": [], \"layout_hint\": \"body\"}, {\"unit_id\": \"p172_b7_l1\", \"page_index\": 172, \"block_id\": 7, \"line_index\": 1, \"source_text\": \"的⾼級管理⼈員。\", \"bbox\": [42.37, 301.644, 105.81, 312.285], \"page_rect\": [0.0, 0.0, 595.28, 841.89], \"font_size\": 8.0, \"font\": \"MicrosoftJhengHeiRegular\", \"ascii_tokens\": [], \"cjk_char_count\": 5, \"preserve_tokens\": [], \"layout_hint\": \"short_label\"}, {\"unit_id\": \"p172_b8_l0\", \"page_index\": 172, \"block_id\": 8, \"line_index\": 0, \"source_text\": \"集團聲譽風險管理委員會負責就對集團構成影響的重⼤聲譽風險事宜提\", \"bbox\": [42.37, 317.744, 287.97, 328.385], \"page_rect\": [0.0, 0.0, 595.28, 841.89], \"font_size\": 8.0, \"font\": \"MicrosoftJhengHeiRegular\", \"ascii_tokens\": [], \"cjk_char_count\": 30, \"preserve_tokens\": [], \"layout_hint\": \"body\"}, {\"unit_id\": \"p172_b8_l1\", \"page_index\": 172, \"block_id\": 8, \"line_index\": 1, \"source_text\": \"供建議及意⾒。\", \"bbox\": [42.37, 327.344, 97.89, 337.985], \"page_rect\": [0.0, 0.0, 595.28, 841.89], \"font_size\": 8.0, \"font\": \"MicrosoftJhengHeiRegular\", \"ascii_tokens\": [], \"cjk_char_count\": 5, \"preserve_tokens\": [], \"layout_hint\": \"short_label\"}, {\"unit_id\": \"p172_b9_l0\", \"page_index\": 172, \"block_id\": 9, \"line_index\": 0, \"source_text\": \"環境風險管理督導會議負責監督環境風險及漂綠風險。我們已在地區層\", \"bbox\": [42.37, 343.444, 287.97, 354.085], \"page_rect\": [0.0, 0.0, 595.28, 841.89], \"font_size\": 8.0, \"font\": \"MicrosoftJhengHeiRegular\", \"ascii_tokens\": [], \"cjk_char_count\": 30, \"preserve_tokens\": [], \"layout_hint\": \"body\"}, {\"unit_id\": \"p172_b9_l1\", \"page_index\": 172, \"block_id\": 9, \"line_index\": 1, \"source_text\": \"⾯設立具有同等職能的論壇，並會持續發展集團的管治及監督⽅針。\", \"bbox\": [42.37, 353.044, 280.05, 363.685], \"page_rect\": [0.0, 0.0, 595.28, 841.89], \"font_size\": 8.0, \"font\": \"MicrosoftJhengHeiRegular\", \"ascii_tokens\": [], \"cjk_char_count\": 26, \"preserve_tokens\": [], \"layout_hint\": \"body\"}, {\"unit_id\": \"p172_b10_l0\", \"page_index\": 172, \"block_id\": 10, \"line_index\": 0, \"source_text\": \"集團風險管理會議及集團風險管理委員會收取有關滙豐氣候風險狀況的\", \"bbox\": [42.37, 369.144, 287.97, 379.785], \"page_rect\": [0.0, 0.0, 595.28, 841.89], \"font_size\": 8.0, \"font\": \"MicrosoftJhengHeiRegular\", \"ascii_tokens\": [], \"cjk_char_count\": 31, \"preserve_tokens\": [], \"layout_hint\": \"body\"}, {\"unit_id\": \"p172_b10_l1\", \"page_index\": 172, \"block_id\": 10, \"line_index\": 1, \"source_text\": \"最新報告。\", \"bbox\": [42.37, 378.744, 82.05, 389.385], \"page_rect\": [0.0, 0.0, 595.28, 841.89], \"font_size\": 8.0, \"font\": \"MicrosoftJhengHeiRegular\", \"ascii_tokens\": [], \"cjk_char_count\": 4, \"preserve_tokens\": [], \"layout_hint\": \"short_label\"}, {\"unit_id\": \"p172_b11_l0\", \"page_index\": 172, \"block_id\": 11, \"line_index\": 0, \"source_text\": \"Ñ 有關集團環境、社會及管治的管治架構詳情，請參閱第58⾴。\", \"bbox\": [42.37, 394.91, 243.816, 405.158], \"page_rect\": [0.0, 0.0, 595.28, 841.89], \"font_size\": 9.0, \"font\": \"Wingdings3\", \"ascii_tokens\": [], \"cjk_char_count\": 22, \"preserve_tokens\": [], \"layout_hint\": \"body\"}, {\"unit_id\": \"p172_b12_l0\", \"page_index\": 172, \"block_id\": 12, \"line_index\": 0, \"source_text\": \"承受風險⽔平\", \"bbox\": [42.37, 410.652, 114.37, 426.612], \"page_rect\": [0.0, 0.0, 595.28, 841.89], \"font_size\": 12.0, \"font\": \"MicrosoftJhengHeiRegular\", \"ascii_tokens\": [], \"cjk_char_count\": 5, \"preserve_tokens\": [], \"layout_hint\": \"short_label\"}, {\"unit_id\": \"p172_b12_l1\", \"page_index\": 172, \"block_id\": 12, \"line_index\": 1, \"source_text\": \"集團承受氣候風險⽔平聲明構成集團承受風險⽔平聲明⼀部分，並由董\", \"bbox\": [42.37, 426.794, 287.97, 437.435], \"page_rect\": [0.0, 0.0, 595.28, 841.89], \"font_size\": 8.0, \"font\": \"MicrosoftJhengHeiRegular\", \"ascii_tokens\": [], \"cjk_char_count\": 27, \"preserve_tokens\": [], \"layout_hint\": \"body\"}, {\"unit_id\": \"p172_b12_l2\", \"page_index\": 172, \"block_id\": 12, \"line_index\": 2, \"source_text\": \"事會批准及監督，有助業務以有效及可持續⽅式實現淨零抱負，並每年\", \"bbox\": [42.37, 436.394, 287.97, 447.035], \"page_rect\": [0.0, 0.0, 595.28, 841.89], \"font_size\": 8.0, \"font\": \"MicrosoftJhengHeiRegular\", \"ascii_tokens\": [], \"cjk_char_count\": 28, \"preserve_tokens\": [], \"layout_hint\": \"body\"}, {\"unit_id\": \"p172_b12_l3\", \"page_index\": 172, \"block_id\": 12, \"line_index\": 3, \"source_text\": \"進⾏檢討，倘發⽣違規情況則提前進⾏有關審視。\", \"bbox\": [42.37, 445.994, 216.69, 456.635], \"page_rect\": [0.0, 0.0, 595.28, 841.89], \"font_size\": 8.0, \"font\": \"MicrosoftJhengHeiRegular\", \"ascii_tokens\": [], \"cjk_char_count\": 17, \"preserve_tokens\": [], \"layout_hint\": \"short_label\"}, {\"unit_id\": \"p172_b13_l0\", \"page_index\": 172, \"block_id\": 13, \"line_index\": 0, \"source_text\": \"氣候風險指標按季呈報，以便集團風險管理會議及集團風險管理委員會\", \"bbox\": [42.37, 462.094, 287.97, 472.735], \"page_rect\": [0.0, 0.0, 595.28, 841.89], \"font_size\": 8.0, \"font\": \"MicrosoftJhengHeiRegular\", \"ascii_tokens\": [], \"cjk_char_count\": 30, \"preserve_tokens\": [], \"layout_hint\": \"body\"}, {\"unit_id\": \"p172_b13_l1\", \"page_index\": 172, \"block_id\": 13, \"line_index\": 1, \"source_text\": \"監督。\", \"bbox\": [42.37, 471.694, 66.21, 482.335], \"page_rect\": [0.0, 0.0, 595.28, 841.89], \"font_size\": 8.0, \"font\": \"MicrosoftJhengHeiRegular\", \"ascii_tokens\": [], \"cjk_char_count\": 2, \"preserve_tokens\": [], \"layout_hint\": \"short_label\"}, {\"unit_id\": \"p172_b14_l0\", \"page_index\": 172, \"block_id\": 14, \"line_index\": 0, \"source_text\": \"政策、程序及監控\", \"bbox\": [304.57, 89.702, 400.57, 105.662], \"page_rect\": [0.0, 0.0, 595.28, 841.89], \"font_size\": 12.0, \"font\": \"MicrosoftJhengHeiRegular\", \"ascii_tokens\": [], \"cjk_char_count\": 7, \"preserve_tokens\": [], \"layout_hint\": \"short_label\"}, {\"unit_id\": \"p172_b14_l1\", \"page_index\": 172, \"block_id\": 14, \"line_index\": 1, \"source_text\": \"我們繼續更新及將氣候風險納入集團眾多範疇的政策、程序及監控措\", \"bbox\": [304.57, 105.844, 542.25, 116.485], \"page_rect\": [0.0, 0.0, 595.28, 841.89], \"font_size\": 8.0, \"font\": \"MicrosoftJhengHeiRegular\", \"ascii_tokens\": [], \"cjk_char_count\": 29, \"preserve_tokens\": [], \"layout_hint\": \"body\"}, {\"unit_id\": \"p172_b14_l2\", \"page_index\": 172, \"block_id\": 14, \"line_index\": 2, \"source_text\": \"施。\", \"bbox\": [304.57, 115.444, 320.49, 126.085], \"page_rect\": [0.0, 0.0, 595.28, 841.89], \"font_size\": 8.0, \"font\": \"MicrosoftJhengHeiRegular\", \"ascii_tokens\": [], \"cjk_char_count\": 1, \"preserve_tokens\": [], \"layout_hint\": \"short_label\"}, {\"unit_id\": \"p172_b15_l0\", \"page_index\": 172, \"block_id\": 15, \"line_index\": 0, \"source_text\": \"Ñ 有關我們如何管理業務分部氣候風險的詳情，請參閱第50⾴。\", \"bbox\": [304.57, 131.61, 506.016, 141.858], \"page_rect\": [0.0, 0.0, 595.28, 841.89], \"font_size\": 9.0, \"font\": \"Wingdings3\", \"ascii_tokens\": [], \"cjk_char_count\": 23, \"preserve_tokens\": [], \"layout_hint\": \"body\"}, {\"unit_id\": \"p172_b16_l0\", \"page_index\": 172, \"block_id\": 16, \"line_index\": 0, \"source_text\": \"整合氣候風險管理⽅針\", \"bbox\": [304.57, 155.981, 444.57, 174.602], \"page_rect\": [0.0, 0.0, 595.28, 841.89], \"font_size\": 14.0, \"font\": \"MicrosoftJhengHeiRegular\", \"ascii_tokens\": [], \"cjk_char_count\": 9, \"preserve_tokens\": [], \"layout_hint\": \"heading\"}, {\"unit_id\": \"p172_b17_l0\", \"page_index\": 172, \"block_id\": 17, \"line_index\": 0, \"source_text\": \"下文詳述滙豐如何將氣候風險管理整合⾄各主要風險類別。有關內部境\", \"bbox\": [304.57, 177.895, 550.17, 188.535], \"page_rect\": [0.0, 0.0, 595.28, 841.89], \"font_size\": 8.0, \"font\": \"MicrosoftJhengHeiRegular\", \"ascii_tokens\": [], \"cjk_char_count\": 29, \"preserve_tokens\": [], \"layout_hint\": \"body\"}, {\"unit_id\": \"p172_b17_l1\", \"page_index\": 172, \"block_id\": 17, \"line_index\": 1, \"source_text\": \"況分析的詳情，請參閱第173⾴「氣候境況分析之⾒解」⼀節。\", \"bbox\": [304.57, 187.495, 524.226, 198.135], \"page_rect\": [0.0, 0.0, 595.28, 841.89], \"font_size\": 8.0, \"font\": \"MicrosoftJhengHeiRegular\", \"ascii_tokens\": [], \"cjk_char_count\": 19, \"preserve_tokens\": [], \"layout_hint\": \"body\"}, {\"unit_id\": \"p172_b18_l0\", \"page_index\": 172, \"block_id\": 18, \"line_index\": 0, \"source_text\": \"批發信貸風險\", \"bbox\": [304.57, 202.666, 382.57, 219.957], \"page_rect\": [0.0, 0.0, 595.28, 841.89], \"font_size\": 13.0, \"font\": \"MicrosoftJhengHeiRegular\", \"ascii_tokens\": [], \"cjk_char_count\": 6, \"preserve_tokens\": [], \"layout_hint\": \"short_label\"}, {\"unit_id\": \"p172_b19_l0\", \"page_index\": 172, \"block_id\": 19, \"line_index\": 0, \"source_text\": \"我們已設立衡量指標，監控集團批發企業貸款組合於六個⾼過渡風險⾏\", \"bbox\": [304.57, 220.195, 550.17, 230.835], \"page_rect\": [0.0, 0.0, 595.28, 841.89], \"font_size\": 8.0, \"font\": \"MicrosoftJhengHeiRegular\", \"ascii_tokens\": [], \"cjk_char_count\": 28, \"preserve_tokens\": [], \"layout_hint\": \"body\"}, {\"unit_id\": \"p172_b19_l1\", \"page_index\": 172, \"block_id\": 19, \"line_index\": 1, \"source_text\": \"業的風險承擔（如下表所⽰）。於2025年12⽉31⽇，六個⾼過渡風險\", \"bbox\": [304.57, 229.795, 546.986, 240.435], \"page_rect\": [0.0, 0.0, 595.28, 841.89], \"font_size\": 8.0, \"font\": \"MicrosoftJhengHeiRegular\", \"ascii_tokens\": [], \"cjk_char_count\": 18, \"preserve_tokens\": [{\"type\": \"currency_amount\", \"value\": \"31\"}], \"layout_hint\": \"body\"}, {\"unit_id\": \"p172_b19_l2\", \"page_index\": 172, \"block_id\": 19, \"line_index\": 2, \"source_text\": \"⾏業的整體風險承擔佔批發貸款賬⾯總值總計的17.5%。有關披露資料\", \"bbox\": [304.57, 239.395, 548.786, 250.035], \"page_rect\": [0.0, 0.0, 595.28, 841.89], \"font_size\": 8.0, \"font\": \"MicrosoftJhengHeiRegular\", \"ascii_tokens\": [], \"cjk_char_count\": 25, \"preserve_tokens\": [{\"type\": \"percentage\", \"value\": \"17.5%\"}], \"layout_hint\": \"body\"}, {\"unit_id\": \"p172_b19_l3\", \"page_index\": 172, \"block_id\": 19, \"line_index\": 3, \"source_text\": \"涵蓋⾏業的整條價值鏈。⾏業分類根據滙豐內部的界定，適⽤於⼀組可\", \"bbox\": [304.57, 248.995, 550.17, 259.635], \"page_rect\": [0.0, 0.0, 595.28, 841.89], \"font_size\": 8.0, \"font\": \"MicrosoftJhengHeiRegular\", \"ascii_tokens\": [], \"cjk_char_count\": 25, \"preserve_tokens\": [], \"layout_hint\": \"body\"}, {\"unit_id\": \"p172_b19_l4\", \"page_index\": 172, \"block_id\": 19, \"line_index\": 4, \"source_text\": \"判斷業務性質的交易對⼿。我們利⽤可得的公開數據、內部數據及相關\", \"bbox\": [304.57, 258.595, 550.17, 269.235], \"page_rect\": [0.0, 0.0, 595.28, 841.89], \"font_size\": 8.0, \"font\": \"MicrosoftJhengHeiRegular\", \"ascii_tokens\": [], \"cjk_char_count\": 27, \"preserve_tokens\": [], \"layout_hint\": \"body\"}, {\"unit_id\": \"p172_b19_l5\", \"page_index\": 172, \"block_id\": 19, \"line_index\": 5, \"source_text\": \"專家意⾒釐定合適的⾏業。隨著數據質素持續改善，並不斷提升相關程\", \"bbox\": [304.57, 268.194, 550.17, 278.835], \"page_rect\": [0.0, 0.0, 595.28, 841.89], \"font_size\": 8.0, \"font\": \"MicrosoftJhengHeiRegular\", \"ascii_tokens\": [], \"cjk_char_count\": 27, \"preserve_tokens\": [], \"layout_hint\": \"body\"}, {\"unit_id\": \"p172_b19_l6\", \"page_index\": 172, \"block_id\": 19, \"line_index\": 6, \"source_text\": \"序，⾏業分類將作調整。有關數據將於未來數年持續調整。\", \"bbox\": [304.57, 277.794, 510.57, 288.435], \"page_rect\": [0.0, 0.0, 595.28, 841.89], \"font_size\": 8.0, \"font\": \"MicrosoftJhengHeiRegular\", \"ascii_tokens\": [], \"cjk_char_count\": 22, \"preserve_tokens\": [], \"layout_hint\": \"body\"}, {\"unit_id\": \"p172_b20_l0\", \"page_index\": 172, \"block_id\": 20, \"line_index\": 0, \"source_text\": \"集團客⼾經理透過過渡參與問卷與重要批發貸款客⼾（包括較⾼過渡風\", \"bbox\": [304.57, 293.894, 550.17, 304.535], \"page_rect\": [0.0, 0.0, 595.28, 841.89], \"font_size\": 8.0, \"font\": \"MicrosoftJhengHeiRegular\", \"ascii_tokens\": [], \"cjk_char_count\": 27, \"preserve_tokens\": [], \"layout_hint\": \"body\"}, {\"unit_id\": \"p172_b20_l1\", \"page_index\": 172, \"block_id\": 20, \"line_index\": 1, \"source_text\": \"險⾏業的客⼾）溝通。過渡參與問卷覆蓋所有地區，有助收集資料及評\", \"bbox\": [304.57, 303.494, 550.17, 314.135], \"page_rect\": [0.0, 0.0, 595.28, 841.89], \"font_size\": 8.0, \"font\": \"MicrosoftJhengHeiRegular\", \"ascii_tokens\": [], \"cjk_char_count\": 26, \"preserve_tokens\": [], \"layout_hint\": \"body\"}, {\"unit_id\": \"p172_b20_l2\", \"page_index\": 172, \"block_id\": 20, \"line_index\": 2, \"source_text\": \"估批發貸款客⼾業務模式過渡⾄淨零的情況，以及涉及的相關實體及過\", \"bbox\": [304.57, 313.094, 550.17, 323.735], \"page_rect\": [0.0, 0.0, 595.28, 841.89], \"font_size\": 8.0, \"font\": \"MicrosoftJhengHeiRegular\", \"ascii_tokens\": [], \"cjk_char_count\": 28, \"preserve_tokens\": [], \"layout_hint\": \"body\"}, {\"unit_id\": \"p172_b20_l3\", \"page_index\": 172, \"block_id\": 20, \"line_index\": 3, \"source_text\": \"渡風險。我們以問卷所得回應協助對重要批發貸款客⼾進⾏風險評估。\", \"bbox\": [304.57, 322.694, 550.17, 333.335], \"page_rect\": [0.0, 0.0, 595.28, 841.89], \"font_size\": 8.0, \"font\": \"MicrosoftJhengHeiRegular\", \"ascii_tokens\": [], \"cjk_char_count\": 27, \"preserve_tokens\": [], \"layout_hint\": \"body\"}, {\"unit_id\": \"p172_b21_l0\", \"page_index\": 172, \"block_id\": 21, \"line_index\": 0, \"source_text\": \"滙豐信貸政策規定，客⼾經理須在新資⾦信貸申請及年度信貸檢討中就\", \"bbox\": [304.57, 338.794, 550.17, 349.435], \"page_rect\": [0.0, 0.0, 595.28, 841.89], \"font_size\": 8.0, \"font\": \"MicrosoftJhengHeiRegular\", \"ascii_tokens\": [], \"cjk_char_count\": 28, \"preserve_tokens\": [], \"layout_hint\": \"body\"}, {\"unit_id\": \"p172_b21_l1\", \"page_index\": 172, \"block_id\": 21, \"line_index\": 1, \"source_text\": \"氣候風險因素作出評註。集團的信貸政策亦規定，如負責⼈員認為氣候\", \"bbox\": [304.57, 348.394, 550.17, 359.035], \"page_rect\": [0.0, 0.0, 595.28, 841.89], \"font_size\": 8.0, \"font\": \"MicrosoftJhengHeiRegular\", \"ascii_tokens\": [], \"cjk_char_count\": 28, \"preserve_tokens\": [], \"layout_hint\": \"body\"}, {\"unit_id\": \"p172_b21_l2\", \"page_index\": 172, \"block_id\": 21, \"line_index\": 2, \"source_text\": \"將於12個⽉內對信貸風險產⽣重⼤影響，⽽原有信貸風險評級未能反\", \"bbox\": [304.57, 357.994, 543.434, 368.635], \"page_rect\": [0.0, 0.0, 595.28, 841.89], \"font_size\": 8.0, \"font\": \"MicrosoftJhengHeiRegular\", \"ascii_tokens\": [], \"cjk_char_count\": 24, \"preserve_tokens\": [], \"layout_hint\": \"body\"}, {\"unit_id\": \"p172_b21_l3\", \"page_index\": 172, \"block_id\": 21, \"line_index\": 3, \"source_text\": \"映，則須由相關⼈員調整信貸風險評級。\", \"bbox\": [304.57, 367.594, 447.21, 378.235], \"page_rect\": [0.0, 0.0, 595.28, 841.89], \"font_size\": 8.0, \"font\": \"MicrosoftJhengHeiRegular\", \"ascii_tokens\": [], \"cjk_char_count\": 15, \"preserve_tokens\": [], \"layout_hint\": \"short_label\"}, {\"unit_id\": \"p172_b22_l0\", \"page_index\": 172, \"block_id\": 22, \"line_index\": 0, \"source_text\": \"滙豐於2025年繼續發展信貸風險管理⽅針，並為客⼾經理修訂氣候風險\", \"bbox\": [304.57, 383.694, 552.538, 394.335], \"page_rect\": [0.0, 0.0, 595.28, 841.89], \"font_size\": 8.0, \"font\": \"MicrosoftJhengHeiRegular\", \"ascii_tokens\": [], \"cjk_char_count\": 26, \"preserve_tokens\": [], \"layout_hint\": \"body\"}, {\"unit_id\": \"p172_b22_l1\", \"page_index\": 172, \"block_id\": 22, \"line_index\": 1, \"source_text\": \"管理指引，將氣候風險考慮因素進⼀步整合⾄信貸風險評估程序。\", \"bbox\": [304.57, 393.294, 534.33, 403.935], \"page_rect\": [0.0, 0.0, 595.28, 841.89], \"font_size\": 8.0, \"font\": \"MicrosoftJhengHeiRegular\", \"ascii_tokens\": [], \"cjk_char_count\": 25, \"preserve_tokens\": [], \"layout_hint\": \"body\"}, {\"unit_id\": \"p172_b23_l0\", \"page_index\": 172, \"block_id\": 23, \"line_index\": 0, \"source_text\": \"將氣候風險進⼀步納入信貸風險管理的主要挑戰，在於能否獲得⾜夠的\", \"bbox\": [304.57, 409.394, 550.17, 420.035], \"page_rect\": [0.0, 0.0, 595.28, 841.89], \"font_size\": 8.0, \"font\": \"MicrosoftJhengHeiRegular\", \"ascii_tokens\": [], \"cjk_char_count\": 28, \"preserve_tokens\": [], \"layout_hint\": \"body\"}, {\"unit_id\": \"p172_b23_l1\", \"page_index\": 172, \"block_id\": 23, \"line_index\": 1, \"source_text\": \"實體風險數據，從⽽評估批發貸款客⼾所受的影響。\", \"bbox\": [304.57, 418.994, 486.81, 429.635], \"page_rect\": [0.0, 0.0, 595.28, 841.89], \"font_size\": 8.0, \"font\": \"MicrosoftJhengHeiRegular\", \"ascii_tokens\": [], \"cjk_char_count\": 19, \"preserve_tokens\": [], \"layout_hint\": \"short_label\"}, {\"unit_id\": \"p172_b24_l0\", \"page_index\": 172, \"block_id\": 24, \"line_index\": 0, \"source_text\": \"策略報告\", \"bbox\": [44.37, 15.84, 72.37, 25.151], \"page_rect\": [0.0, 0.0, 595.28, 841.89], \"font_size\": 7.0, \"font\": \"MicrosoftJhengHeiRegular\", \"ascii_tokens\": [], \"cjk_char_count\": 4, \"preserve_tokens\": [], \"layout_hint\": \"short_label\"}, {\"unit_id\": \"p172_b24_l1\", \"page_index\": 172, \"block_id\": 24, \"line_index\": 1, \"source_text\": \"環境、社會及\", \"bbox\": [117.87, 15.84, 159.87, 25.151], \"page_rect\": [0.0, 0.0, 595.28, 841.89], \"font_size\": 7.0, \"font\": \"MicrosoftJhengHeiRegular\", \"ascii_tokens\": [], \"cjk_char_count\": 5, \"preserve_tokens\": [], \"layout_hint\": \"short_label\"}, {\"unit_id\": \"p172_b24_l2\", \"page_index\": 172, \"block_id\": 24, \"line_index\": 2, \"source_text\": \"管治報告\", \"bbox\": [117.87, 24.24, 145.87, 33.551], \"page_rect\": [0.0, 0.0, 595.28, 841.89], \"font_size\": 7.0, \"font\": \"MicrosoftJhengHeiRegular\", \"ascii_tokens\": [], \"cjk_char_count\": 4, \"preserve_tokens\": [], \"layout_hint\": \"short_label\"}, {\"unit_id\": \"p172_b24_l3\", \"page_index\": 172, \"block_id\": 24, \"line_index\": 3, \"source_text\": \"財務回顧\", \"bbox\": [191.37, 15.84, 219.37, 25.151], \"page_rect\": [0.0, 0.0, 595.28, 841.89], \"font_size\": 7.0, \"font\": \"MicrosoftJhengHeiRegular\", \"ascii_tokens\": [], \"cjk_char_count\": 4, \"preserve_tokens\": [], \"layout_hint\": \"short_label\"}, {\"unit_id\": \"p172_b24_l4\", \"page_index\": 172, \"block_id\": 24, \"line_index\": 4, \"source_text\": \"風險回顧\", \"bbox\": [264.87, 15.84, 292.87, 25.151], \"page_rect\": [0.0, 0.0, 595.28, 841.89], \"font_size\": 7.0, \"font\": \"MicrosoftJhengHeiBold\", \"ascii_tokens\": [], \"cjk_char_count\": 4, \"preserve_tokens\": [], \"layout_hint\": \"short_label\"}, {\"unit_id\": \"p172_b24_l5\", \"page_index\": 172, \"block_id\": 24, \"line_index\": 5, \"source_text\": \"企業管治報告\", \"bbox\": [338.37, 15.84, 378.935, 25.151], \"page_rect\": [0.0, 0.0, 595.28, 841.89], \"font_size\": 7.0, \"font\": \"MicrosoftJhengHeiRegular\", \"ascii_tokens\": [], \"cjk_char_count\": 6, \"preserve_tokens\": [], \"layout_hint\": \"short_label\"}, {\"unit_id\": \"p172_b24_l6\", \"page_index\": 172, \"block_id\": 24, \"line_index\": 6, \"source_text\": \"財務報表\", \"bbox\": [411.87, 15.84, 439.87, 25.151], \"page_rect\": [0.0, 0.0, 595.28, 841.89], \"font_size\": 7.0, \"font\": \"MicrosoftJhengHeiRegular\", \"ascii_tokens\": [], \"cjk_char_count\": 4, \"preserve_tokens\": [], \"layout_hint\": \"short_label\"}, {\"unit_id\": \"p172_b24_l7\", \"page_index\": 172, \"block_id\": 24, \"line_index\": 7, \"source_text\": \"補充資料\", \"bbox\": [485.37, 15.84, 513.37, 25.151], \"page_rect\": [0.0, 0.0, 595.28, 841.89], \"font_size\": 7.0, \"font\": \"MicrosoftJhengHeiRegular\", \"ascii_tokens\": [], \"cjk_char_count\": 4, \"preserve_tokens\": [], \"layout_hint\": \"short_label\"}, {\"unit_id\": \"p172_b25_l0\", \"page_index\": 172, \"block_id\": 25, \"line_index\": 0, \"source_text\": \"氣候風險\", \"bbox\": [264.87, 36.9, 292.87, 46.211], \"page_rect\": [0.0, 0.0, 595.28, 841.89], \"font_size\": 7.0, \"font\": \"MicrosoftJhengHeiRegular\", \"ascii_tokens\": [], \"cjk_char_count\": 4, \"preserve_tokens\": [], \"layout_hint\": \"short_label\"}, {\"unit_id\": \"p172_b26_l0\", \"page_index\": 172, \"block_id\": 26, \"line_index\": 0, \"source_text\": \"滙豐控股有限公司 2025年報及賬⽬\", \"bbox\": [244.02, 808.67, 352.982, 817.981], \"page_rect\": [0.0, 0.0, 595.28, 841.89], \"font_size\": 7.0, \"font\": \"MicrosoftJhengHeiBold\", \"ascii_tokens\": [], \"cjk_char_count\": 12, \"preserve_tokens\": [], \"layout_hint\": \"short_label\"}, {\"unit_id\": \"p173_b0_l0\", \"page_index\": 173, \"block_id\": 0, \"line_index\": 0, \"source_text\": \"於2025年12⽉31⽇的⾼過渡風險⾏業批發貸款風險承擔\", \"bbox\": [42.73, 72.215, 239.786, 82.855], \"page_rect\": [0.0, 0.0, 595.28, 841.89], \"font_size\": 8.0, \"font\": \"MicrosoftJhengHeiRegular\", \"ascii_tokens\": [], \"cjk_char_count\": 16, \"preserve_tokens\": [{\"type\": \"currency_amount\", \"value\": \"31\"}], \"layout_hint\": \"body\"}, {\"unit_id\": \"p173_b1_l0\", \"page_index\": 173, \"block_id\": 1, \"line_index\": 0, \"source_text\": \"單位\", \"bbox\": [199.74, 92.09, 213.74, 101.401], \"page_rect\": [0.0, 0.0, 595.28, 841.89], \"font_size\": 7.0, \"font\": \"MicrosoftJhengHeiBold\", \"ascii_tokens\": [], \"cjk_char_count\": 2, \"preserve_tokens\": [], \"layout_hint\": \"short_label\"}, {\"unit_id\": \"p173_b1_l1\", \"page_index\": 173, \"block_id\": 1, \"line_index\": 1, \"source_text\": \"汽⾞\", \"bbox\": [247.74, 92.09, 261.74, 101.401], \"page_rect\": [0.0, 0.0, 595.28, 841.89], \"font_size\": 7.0, \"font\": \"MicrosoftJhengHeiBold\", \"ascii_tokens\": [], \"cjk_char_count\": 1, \"preserve_tokens\": [], \"layout_hint\": \"short_label\"}, {\"unit_id\": \"p173_b1_l2\", \"page_index\": 173, \"block_id\": 1, \"line_index\": 2, \"source_text\": \"化⼯\", \"bbox\": [295.74, 92.09, 309.74, 101.401], \"page_rect\": [0.0, 0.0, 595.28, 841.89], \"font_size\": 7.0, \"font\": \"MicrosoftJhengHeiBold\", \"ascii_tokens\": [], \"cjk_char_count\": 1, \"preserve_tokens\": [], \"layout_hint\": \"short_label\"}, {\"unit_id\": \"p173_b2_l0\", \"page_index\": 173, \"block_id\": 2, \"line_index\": 0, \"source_text\": \"建造、承建\", \"bbox\": [322.74, 83.69, 357.74, 93.001], \"page_rect\": [0.0, 0.0, 595.28, 841.89], \"font_size\": 7.0, \"font\": \"MicrosoftJhengHeiBold\", \"ascii_tokens\": [], \"cjk_char_count\": 4, \"preserve_tokens\": [], \"layout_hint\": \"short_label\"}, {\"unit_id\": \"p173_b2_l1\", \"page_index\": 173, \"block_id\": 2, \"line_index\": 1, \"source_text\": \"及建築材料\", \"bbox\": [322.74, 92.09, 357.74, 101.401], \"page_rect\": [0.0, 0.0, 595.28, 841.89], \"font_size\": 7.0, \"font\": \"MicrosoftJhengHeiBold\", \"ascii_tokens\": [], \"cjk_char_count\": 5, \"preserve_tokens\": [], \"layout_hint\": \"short_label\"}, {\"unit_id\": \"p173_b3_l0\", \"page_index\": 173, \"block_id\": 3, \"line_index\": 0, \"source_text\": \"⾦屬及\", \"bbox\": [384.74, 83.69, 405.74, 93.001], \"page_rect\": [0.0, 0.0, 595.28, 841.89], \"font_size\": 7.0, \"font\": \"MicrosoftJhengHeiBold\", \"ascii_tokens\": [], \"cjk_char_count\": 2, \"preserve_tokens\": [], \"layout_hint\": \"short_label\"}, {\"unit_id\": \"p173_b3_l1\", \"page_index\": 173, \"block_id\": 3, \"line_index\": 1, \"source_text\": \"採礦\", \"bbox\": [391.74, 92.09, 405.74, 101.401], \"page_rect\": [0.0, 0.0, 595.28, 841.89], \"font_size\": 7.0, \"font\": \"MicrosoftJhengHeiBold\", \"ascii_tokens\": [], \"cjk_char_count\": 2, \"preserve_tokens\": [], \"layout_hint\": \"short_label\"}, {\"unit_id\": \"p173_b4_l0\", \"page_index\": 173, \"block_id\": 4, \"line_index\": 0, \"source_text\": \"⽯油及\", \"bbox\": [432.74, 83.69, 453.74, 93.001], \"page_rect\": [0.0, 0.0, 595.28, 841.89], \"font_size\": 7.0, \"font\": \"MicrosoftJhengHeiBold\", \"ascii_tokens\": [], \"cjk_char_count\": 2, \"preserve_tokens\": [], \"layout_hint\": \"short_label\"}, {\"unit_id\": \"p173_b4_l1\", \"page_index\": 173, \"block_id\": 4, \"line_index\": 1, \"source_text\": \"天然氣\", \"bbox\": [432.74, 92.09, 453.74, 101.401], \"page_rect\": [0.0, 0.0, 595.28, 841.89], \"font_size\": 7.0, \"font\": \"MicrosoftJhengHeiBold\", \"ascii_tokens\": [], \"cjk_char_count\": 3, \"preserve_tokens\": [], \"layout_hint\": \"short_label\"}, {\"unit_id\": \"p173_b5_l0\", \"page_index\": 173, \"block_id\": 5, \"line_index\": 0, \"source_text\": \"電⼒及\", \"bbox\": [480.74, 83.69, 501.74, 93.001], \"page_rect\": [0.0, 0.0, 595.28, 841.89], \"font_size\": 7.0, \"font\": \"MicrosoftJhengHeiBold\", \"ascii_tokens\": [], \"cjk_char_count\": 2, \"preserve_tokens\": [], \"layout_hint\": \"short_label\"}, {\"unit_id\": \"p173_b5_l1\", \"page_index\": 173, \"block_id\": 5, \"line_index\": 1, \"source_text\": \"公⽤事業\", \"bbox\": [473.74, 92.09, 501.74, 101.401], \"page_rect\": [0.0, 0.0, 595.28, 841.89], \"font_size\": 7.0, \"font\": \"MicrosoftJhengHeiBold\", \"ascii_tokens\": [], \"cjk_char_count\": 3, \"preserve_tokens\": [], \"layout_hint\": \"short_label\"}, {\"unit_id\": \"p173_b5_l2\", \"page_index\": 173, \"block_id\": 5, \"line_index\": 2, \"source_text\": \"總計\", \"bbox\": [535.74, 92.09, 549.74, 101.401], \"page_rect\": [0.0, 0.0, 595.28, 841.89], \"font_size\": 7.0, \"font\": \"MicrosoftJhengHeiBold\", \"ascii_tokens\": [], \"cjk_char_count\": 2, \"preserve_tokens\": [], \"layout_hint\": \"short_label\"}, {\"unit_id\": \"p173_b6_l0\", \"page_index\": 173, \"block_id\": 6, \"line_index\": 0, \"source_text\": \"批發貸款風險承擔1,2,3,4\", \"bbox\": [45.0, 103.34, 114.668, 112.651], \"page_rect\": [0.0, 0.0, 595.28, 841.89], \"font_size\": 7.0, \"font\": \"MicrosoftJhengHeiRegular\", \"ascii_tokens\": [], \"cjk_char_count\": 8, \"preserve_tokens\": [{\"type\": \"currency_amount\", \"value\": \"2,3,4\"}], \"layout_hint\": \"short_label\"}, {\"unit_id\": \"p173_b6_l1\", \"page_index\": 173, \"block_id\": 6, \"line_index\": 1, \"source_text\": \"⼗億美元\", \"bbox\": [185.74, 103.34, 220.75, 112.651], \"page_rect\": [0.0, 0.0, 595.28, 841.89], \"font_size\": 7.0, \"font\": \"MicrosoftJhengHeiBold\", \"ascii_tokens\": [], \"cjk_char_count\": 3, \"preserve_tokens\": [], \"layout_hint\": \"short_label\"}, {\"unit_id\": \"p173_b7_l1\", \"page_index\": 173, \"block_id\": 7, \"line_index\": 1, \"source_text\": \"表中所⽰⾦額亦包括⽀持過渡⾄淨零經濟之綠⾊及其他可持續發展融資貸款。隨著可得數據增加並獲納入我們的風險管理系統及程序，我們就⾼過渡風險⾏業所涉風險\", \"bbox\": [53.71, 120.83, 552.614, 130.141], \"page_rect\": [0.0, 0.0, 595.28, 841.89], \"font_size\": 7.0, \"font\": \"MicrosoftJhengHeiRegular\", \"ascii_tokens\": [], \"cjk_char_count\": 64, \"preserve_tokens\": [], \"layout_hint\": \"body\"}, {\"unit_id\": \"p173_b7_l2\", \"page_index\": 173, \"block_id\": 7, \"line_index\": 2, \"source_text\": \"承擔的計量⽅法及過渡風險衡量指標將隨著時間演變。我們旨在開發合適的系統、數據及程序，以便未來數年加強資料披露。\", \"bbox\": [53.71, 129.23, 429.638, 138.541], \"page_rect\": [0.0, 0.0, 595.28, 841.89], \"font_size\": 7.0, \"font\": \"MicrosoftJhengHeiRegular\", \"ascii_tokens\": [], \"cjk_char_count\": 50, \"preserve_tokens\": [], \"layout_hint\": \"body\"}, {\"unit_id\": \"p173_b7_l4\", \"page_index\": 173, \"block_id\": 7, \"line_index\": 4, \"source_text\": \"我們透過兩步⽅法將交易對⼿分配⾄⾼過渡風險⾏業。⾸先，倘⼀組互有關連交易對⼿的主要業務屬⾼過渡風險⾏業，則無論組內各債務⼈從事何種⾏業，提供予該組\", \"bbox\": [53.71, 137.63, 552.614, 146.941], \"page_rect\": [0.0, 0.0, 595.28, 841.89], \"font_size\": 7.0, \"font\": \"MicrosoftJhengHeiRegular\", \"ascii_tokens\": [], \"cjk_char_count\": 57, \"preserve_tokens\": [], \"layout_hint\": \"body\"}, {\"unit_id\": \"p173_b7_l5\", \"page_index\": 173, \"block_id\": 7, \"line_index\": 5, \"source_text\": \"之所有貸款均須計入⼀個⾼過渡風險⾏業。其次，倘⼀組互有關連交易對⼿的主要業務並非⾼過渡風險⾏業，則僅計入提供予屬⾼過渡風險⾏業之個別債務⼈的貸款。\", \"bbox\": [53.71, 146.03, 552.614, 155.341], \"page_rect\": [0.0, 0.0, 595.28, 841.89], \"font_size\": 7.0, \"font\": \"MicrosoftJhengHeiRegular\", \"ascii_tokens\": [], \"cjk_char_count\": 59, \"preserve_tokens\": [], \"layout_hint\": \"body\"}, {\"unit_id\": \"p173_b7_l6\", \"page_index\": 173, \"block_id\": 7, \"line_index\": 6, \"source_text\": \"⼀組互有關連交易對⼿的主要業務以組內產⽣⼤多數收入的⾏業識別。在以上分配程序中運⽤的客⼾收入數據是最近期可獲得的數據，不會總是與集團本⾝報告期的數\", \"bbox\": [53.71, 154.43, 552.614, 163.741], \"page_rect\": [0.0, 0.0, 595.28, 841.89], \"font_size\": 7.0, \"font\": \"MicrosoftJhengHeiRegular\", \"ascii_tokens\": [], \"cjk_char_count\": 63, \"preserve_tokens\": [], \"layout_hint\": \"body\"}, {\"unit_id\": \"p173_b7_l7\", \"page_index\": 173, \"block_id\": 7, \"line_index\": 7, \"source_text\": \"據保持⼀致。\", \"bbox\": [53.71, 162.83, 94.87, 172.141], \"page_rect\": [0.0, 0.0, 595.28, 841.89], \"font_size\": 7.0, \"font\": \"MicrosoftJhengHeiRegular\", \"ascii_tokens\": [], \"cjk_char_count\": 4, \"preserve_tokens\": [], \"layout_hint\": \"short_label\"}, {\"unit_id\": \"p173_b7_l9\", \"page_index\": 173, \"block_id\": 7, \"line_index\": 9, \"source_text\": \"六個⾼過渡風險⾏業佔同業及客⼾批發貸款賬⾯總值總計6,350億美元的17.5%。⾦額包括持作出售⽤途資產。\", \"bbox\": [53.71, 171.23, 385.307, 180.541], \"page_rect\": [0.0, 0.0, 595.28, 841.89], \"font_size\": 7.0, \"font\": \"MicrosoftJhengHeiRegular\", \"ascii_tokens\": [], \"cjk_char_count\": 35, \"preserve_tokens\": [{\"type\": \"percentage\", \"value\": \"17.5%\"}], \"layout_hint\": \"body\"}, {\"unit_id\": \"p173_b7_l11\", \"page_index\": 173, \"block_id\": 7, \"line_index\": 11, \"source_text\": \"表中所⽰⽤於監察批發企業貸款組合的⾏業，有別於我們在融資項⽬排放⽬標及報告中集中提述的⾏業範疇。後者集中於碳排放最多的⾏業，以及我們認為價值鏈中佔\", \"bbox\": [53.71, 179.63, 552.614, 188.941], \"page_rect\": [0.0, 0.0, 595.28, 841.89], \"font_size\": 7.0, \"font\": \"MicrosoftJhengHeiRegular\", \"ascii_tokens\": [], \"cjk_char_count\": 63, \"preserve_tokens\": [], \"layout_hint\": \"body\"}, {\"unit_id\": \"p173_b7_l12\", \"page_index\": 173, \"block_id\": 7, \"line_index\": 12, \"source_text\": \"⼤部分排放的部分，這有助減少重覆計算。該等⾏業載於第41⾴「融資項⽬排放」⼀節。\", \"bbox\": [53.71, 188.03, 321.264, 197.341], \"page_rect\": [0.0, 0.0, 595.28, 841.89], \"font_size\": 7.0, \"font\": \"MicrosoftJhengHeiRegular\", \"ascii_tokens\": [], \"cjk_char_count\": 28, \"preserve_tokens\": [], \"layout_hint\": \"body\"}, {\"unit_id\": \"p173_b8_l0\", \"page_index\": 173, \"block_id\": 8, \"line_index\": 0, \"source_text\": \"零售信貸風險\", \"bbox\": [42.37, 203.316, 120.37, 220.607], \"page_rect\": [0.0, 0.0, 595.28, 841.89], \"font_size\": 13.0, \"font\": \"MicrosoftJhengHeiRegular\", \"ascii_tokens\": [], \"cjk_char_count\": 6, \"preserve_tokens\": [], \"layout_hint\": \"short_label\"}, {\"unit_id\": \"p173_b9_l0\", \"page_index\": 173, \"block_id\": 9, \"line_index\": 0, \"source_text\": \"主要由於實體風險的影響，氣候風險或會增加環球零售按揭組合的信貸\", \"bbox\": [42.37, 220.845, 287.97, 231.485], \"page_rect\": [0.0, 0.0, 595.28, 841.89], \"font_size\": 8.0, \"font\": \"MicrosoftJhengHeiRegular\", \"ascii_tokens\": [], \"cjk_char_count\": 30, \"preserve_tokens\": [], \"layout_hint\": \"body\"}, {\"unit_id\": \"p173_b9_l1\", \"page_index\": 173, \"block_id\": 9, \"line_index\": 1, \"source_text\": \"虧損，繼⽽影響零售信貸風險。過往兩年進⾏的氣候境況分析顯⽰，由\", \"bbox\": [42.37, 230.445, 287.97, 241.085], \"page_rect\": [0.0, 0.0, 595.28, 841.89], \"font_size\": 8.0, \"font\": \"MicrosoftJhengHeiRegular\", \"ascii_tokens\": [], \"cjk_char_count\": 25, \"preserve_tokens\": [], \"layout_hint\": \"body\"}, {\"unit_id\": \"p173_b9_l2\", \"page_index\": 173, \"block_id\": 9, \"line_index\": 2, \"source_text\": \"於物業的貸款估值狀況相對偏低，加上所在地點及客⼾能夠購買物業保\", \"bbox\": [42.37, 240.045, 287.97, 250.685], \"page_rect\": [0.0, 0.0, 595.28, 841.89], \"font_size\": 8.0, \"font\": \"MicrosoftJhengHeiRegular\", \"ascii_tokens\": [], \"cjk_char_count\": 29, \"preserve_tokens\": [], \"layout_hint\": \"body\"}, {\"unit_id\": \"p173_b9_l3\", \"page_index\": 173, \"block_id\": 9, \"line_index\": 3, \"source_text\": \"險，預計中期⾄2030年⽽⾔，氣候相關風險不會對信貸違責造成重⼤影\", \"bbox\": [42.37, 249.645, 290.338, 260.285], \"page_rect\": [0.0, 0.0, 595.28, 841.89], \"font_size\": 8.0, \"font\": \"MicrosoftJhengHeiRegular\", \"ascii_tokens\": [], \"cjk_char_count\": 23, \"preserve_tokens\": [], \"layout_hint\": \"body\"}, {\"unit_id\": \"p173_b9_l4\", \"page_index\": 173, \"block_id\": 9, \"line_index\": 4, \"source_text\": \"響。物業保險仍然是⼀項緩解措施，但隨著氣候風險增加，加上保險市\", \"bbox\": [42.37, 259.245, 287.97, 269.885], \"page_rect\": [0.0, 0.0, 595.28, 841.89], \"font_size\": 8.0, \"font\": \"MicrosoftJhengHeiRegular\", \"ascii_tokens\": [], \"cjk_char_count\": 27, \"preserve_tokens\": [], \"layout_hint\": \"body\"}, {\"unit_id\": \"p173_b9_l5\", \"page_index\": 173, \"block_id\": 9, \"line_index\": 5, \"source_text\": \"場未來發展⽅向尚屬未知之數，預計相關影響於2030年後⻑期⽽⾔將會\", \"bbox\": [42.37, 268.845, 290.338, 279.485], \"page_rect\": [0.0, 0.0, 595.28, 841.89], \"font_size\": 8.0, \"font\": \"MicrosoftJhengHeiRegular\", \"ascii_tokens\": [], \"cjk_char_count\": 24, \"preserve_tokens\": [], \"layout_hint\": \"body\"}, {\"unit_id\": \"p173_b9_l6\", \"page_index\": 173, \"block_id\": 9, \"line_index\": 6, \"source_text\": \"增加。有關結果被視為引導性，隨著我們的⽅針不斷完善，結果亦會隨\", \"bbox\": [42.37, 278.445, 287.97, 289.085], \"page_rect\": [0.0, 0.0, 595.28, 841.89], \"font_size\": 8.0, \"font\": \"MicrosoftJhengHeiRegular\", \"ascii_tokens\": [], \"cjk_char_count\": 27, \"preserve_tokens\": [], \"layout_hint\": \"body\"}, {\"unit_id\": \"p173_b9_l7\", \"page_index\": 173, \"block_id\": 9, \"line_index\": 7, \"source_text\": \"時間演變。在集團按揭組合內，可能涉及⾼實體風險的物業或範疇在當\", \"bbox\": [42.37, 288.045, 287.97, 298.685], \"page_rect\": [0.0, 0.0, 595.28, 841.89], \"font_size\": 8.0, \"font\": \"MicrosoftJhengHeiRegular\", \"ascii_tokens\": [], \"cjk_char_count\": 28, \"preserve_tokens\": [], \"layout_hint\": \"body\"}, {\"unit_id\": \"p173_b9_l8\", \"page_index\": 173, \"block_id\": 9, \"line_index\": 8, \"source_text\": \"地層⾯予以識別及評估，風險承擔受到監控。物業價值下跌、保險成本\", \"bbox\": [42.37, 297.645, 287.97, 308.285], \"page_rect\": [0.0, 0.0, 595.28, 841.89], \"font_size\": 8.0, \"font\": \"MicrosoftJhengHeiRegular\", \"ascii_tokens\": [], \"cjk_char_count\": 27, \"preserve_tokens\": [], \"layout_hint\": \"body\"}, {\"unit_id\": \"p173_b9_l9\", \"page_index\": 173, \"block_id\": 9, \"line_index\": 9, \"source_text\": \"上升和能否購買保險，⽇後或會對⾼實體風險物業構成負⾯財務影響。\", \"bbox\": [42.37, 307.245, 287.97, 317.885], \"page_rect\": [0.0, 0.0, 595.28, 841.89], \"font_size\": 8.0, \"font\": \"MicrosoftJhengHeiRegular\", \"ascii_tokens\": [], \"cjk_char_count\": 26, \"preserve_tokens\": [], \"layout_hint\": \"body\"}, {\"unit_id\": \"p173_b10_l0\", \"page_index\": 173, \"block_id\": 10, \"line_index\": 0, \"source_text\": \"零售按揭貸款及相關2025年提升措施\", \"bbox\": [42.37, 322.602, 238.21, 338.563], \"page_rect\": [0.0, 0.0, 595.28, 841.89], \"font_size\": 12.0, \"font\": \"MicrosoftJhengHeiRegular\", \"ascii_tokens\": [], \"cjk_char_count\": 14, \"preserve_tokens\": [], \"layout_hint\": \"short_label\"}, {\"unit_id\": \"p173_b10_l1\", \"page_index\": 173, \"block_id\": 10, \"line_index\": 1, \"source_text\": \"按風險承擔計算，英國及香港是我們最重要的按揭市場，截⾄2025年\", \"bbox\": [42.37, 338.745, 282.418, 349.385], \"page_rect\": [0.0, 0.0, 595.28, 841.89], \"font_size\": 8.0, \"font\": \"MicrosoftJhengHeiRegular\", \"ascii_tokens\": [], \"cjk_char_count\": 25, \"preserve_tokens\": [], \"layout_hint\": \"body\"}, {\"unit_id\": \"p173_b10_l2\", \"page_index\": 173, \"block_id\": 10, \"line_index\": 2, \"source_text\": \"12⽉，分別約佔集團環球按揭組合的50%及30%，其餘份額來⾃國際財\", \"bbox\": [42.37, 348.345, 289.602, 358.985], \"page_rect\": [0.0, 0.0, 595.28, 841.89], \"font_size\": 8.0, \"font\": \"MicrosoftJhengHeiRegular\", \"ascii_tokens\": [], \"cjk_char_count\": 22, \"preserve_tokens\": [{\"type\": \"percentage\", \"value\": \"50%\"}, {\"type\": \"percentage\", \"value\": \"30%\"}, {\"type\": \"currency_amount\", \"value\": \"12\"}], \"layout_hint\": \"body\"}, {\"unit_id\": \"p173_b10_l3\", \"page_index\": 173, \"block_id\": 10, \"line_index\": 3, \"source_text\": \"富管理及卓越理財的資本市場業務。過往兩年對英國按揭組合進⾏的賬\", \"bbox\": [42.37, 357.945, 287.97, 368.585], \"page_rect\": [0.0, 0.0, 595.28, 841.89], \"font_size\": 8.0, \"font\": \"MicrosoftJhengHeiRegular\", \"ascii_tokens\": [], \"cjk_char_count\": 29, \"preserve_tokens\": [], \"layout_hint\": \"body\"}, {\"unit_id\": \"p173_b10_l4\", \"page_index\": 173, \"block_id\": 10, \"line_index\": 4, \"source_text\": \"齡分析顯⽰平均尚餘合約期限為22.2年，但由於部分客⼾期內採⽤再融\", \"bbox\": [42.37, 367.545, 287.546, 378.185], \"page_rect\": [0.0, 0.0, 595.28, 841.89], \"font_size\": 8.0, \"font\": \"MicrosoftJhengHeiRegular\", \"ascii_tokens\": [], \"cjk_char_count\": 25, \"preserve_tokens\": [], \"layout_hint\": \"body\"}, {\"unit_id\": \"p173_b10_l5\", \"page_index\": 173, \"block_id\": 10, \"line_index\": 5, \"source_text\": \"資選項，按揭的實際平均期限為五⾄八年，這表⽰集團的氣候風險策略\", \"bbox\": [42.37, 377.145, 287.97, 387.785], \"page_rect\": [0.0, 0.0, 595.28, 841.89], \"font_size\": 8.0, \"font\": \"MicrosoftJhengHeiRegular\", \"ascii_tokens\": [], \"cjk_char_count\": 27, \"preserve_tokens\": [], \"layout_hint\": \"body\"}, {\"unit_id\": \"p173_b10_l6\", \"page_index\": 173, \"block_id\": 10, \"line_index\": 6, \"source_text\": \"⽅針既需考慮短期風險，亦要考慮⻑期前瞻性風險，因為客⼾可能選擇\", \"bbox\": [42.37, 386.745, 287.97, 397.385], \"page_rect\": [0.0, 0.0, 595.28, 841.89], \"font_size\": 8.0, \"font\": \"MicrosoftJhengHeiRegular\", \"ascii_tokens\": [], \"cjk_char_count\": 26, \"preserve_tokens\": [], \"layout_hint\": \"body\"}, {\"unit_id\": \"p173_b10_l7\", \"page_index\": 173, \"block_id\": 10, \"line_index\": 7, \"source_text\": \"在整個貸款期限內保留有關貸款。我們亦對英國、香港及其他市場（包\", \"bbox\": [42.37, 396.345, 287.97, 406.985], \"page_rect\": [0.0, 0.0, 595.28, 841.89], \"font_size\": 8.0, \"font\": \"MicrosoftJhengHeiRegular\", \"ascii_tokens\": [], \"cjk_char_count\": 28, \"preserve_tokens\": [], \"layout_hint\": \"body\"}, {\"unit_id\": \"p173_b10_l8\", \"page_index\": 173, \"block_id\": 10, \"line_index\": 8, \"source_text\": \"括美國和澳洲）進⾏前瞻性氣候境況分析，合共涵蓋集團零售貸款組合\", \"bbox\": [42.37, 405.945, 287.97, 416.585], \"page_rect\": [0.0, 0.0, 595.28, 841.89], \"font_size\": 8.0, \"font\": \"MicrosoftJhengHeiRegular\", \"ascii_tokens\": [], \"cjk_char_count\": 28, \"preserve_tokens\": [], \"layout_hint\": \"body\"}, {\"unit_id\": \"p173_b10_l9\", \"page_index\": 173, \"block_id\": 10, \"line_index\": 9, \"source_text\": \"逾90%。更多詳情，請參閱第176⾴。\", \"bbox\": [42.37, 415.545, 175.13, 426.185], \"page_rect\": [0.0, 0.0, 595.28, 841.89], \"font_size\": 8.0, \"font\": \"MicrosoftJhengHeiRegular\", \"ascii_tokens\": [], \"cjk_char_count\": 9, \"preserve_tokens\": [{\"type\": \"percentage\", \"value\": \"90%\"}], \"layout_hint\": \"short_label\"}, {\"unit_id\": \"p173_b11_l0\", \"page_index\": 173, \"block_id\": 11, \"line_index\": 0, \"source_text\": \"我們繼續完善氣候風險管理⽅針，包括於2025年提升內部氣候風險管理\", \"bbox\": [42.37, 431.645, 290.338, 442.285], \"page_rect\": [0.0, 0.0, 595.28, 841.89], \"font_size\": 8.0, \"font\": \"MicrosoftJhengHeiRegular\", \"ascii_tokens\": [], \"cjk_char_count\": 27, \"preserve_tokens\": [], \"layout_hint\": \"body\"}, {\"unit_id\": \"p173_b11_l1\", \"page_index\": 173, \"block_id\": 11, \"line_index\": 1, \"source_text\": \"政策及相關監控措施，包括強制引入實體風險的關鍵風險管理指標，以\", \"bbox\": [42.37, 441.245, 287.97, 451.885], \"page_rect\": [0.0, 0.0, 595.28, 841.89], \"font_size\": 8.0, \"font\": \"MicrosoftJhengHeiRegular\", \"ascii_tokens\": [], \"cjk_char_count\": 29, \"preserve_tokens\": [], \"layout_hint\": \"body\"}, {\"unit_id\": \"p173_b11_l2\", \"page_index\": 173, \"block_id\": 11, \"line_index\": 2, \"source_text\": \"及在按揭審批決策中引入氣候風險評估。英國業務已透過運⽤第三⽅供\", \"bbox\": [42.37, 450.845, 287.97, 461.485], \"page_rect\": [0.0, 0.0, 595.28, 841.89], \"font_size\": 8.0, \"font\": \"MicrosoftJhengHeiRegular\", \"ascii_tokens\": [], \"cjk_char_count\": 28, \"preserve_tokens\": [], \"layout_hint\": \"body\"}, {\"unit_id\": \"p173_b11_l3\", \"page_index\": 173, \"block_id\": 11, \"line_index\": 3, \"source_text\": \"應商提供的數據，將⽔災及海岸侵蝕相關的實體風險納入既定的按揭決\", \"bbox\": [42.37, 460.445, 287.97, 471.085], \"page_rect\": [0.0, 0.0, 595.28, 841.89], \"font_size\": 8.0, \"font\": \"MicrosoftJhengHeiRegular\", \"ascii_tokens\": [], \"cjk_char_count\": 29, \"preserve_tokens\": [], \"layout_hint\": \"body\"}, {\"unit_id\": \"p173_b11_l4\", \"page_index\": 173, \"block_id\": 11, \"line_index\": 4, \"source_text\": \"策程序。香港業務則已於2025年透過運⽤第三⽅數據，將實體風險考慮\", \"bbox\": [42.37, 470.045, 290.338, 480.685], \"page_rect\": [0.0, 0.0, 595.28, 841.89], \"font_size\": 8.0, \"font\": \"MicrosoftJhengHeiRegular\", \"ascii_tokens\": [], \"cjk_char_count\": 25, \"preserve_tokens\": [], \"layout_hint\": \"body\"}, {\"unit_id\": \"p173_b11_l5\", \"page_index\": 173, \"block_id\": 11, \"line_index\": 5, \"source_text\": \"因素引入按揭審批程序。\", \"bbox\": [42.37, 479.645, 129.57, 490.285], \"page_rect\": [0.0, 0.0, 595.28, 841.89], \"font_size\": 8.0, \"font\": \"MicrosoftJhengHeiRegular\", \"ascii_tokens\": [], \"cjk_char_count\": 10, \"preserve_tokens\": [], \"layout_hint\": \"short_label\"}, {\"unit_id\": \"p173_b12_l0\", \"page_index\": 173, \"block_id\": 12, \"line_index\": 0, \"source_text\": \"實體風險\", \"bbox\": [42.37, 495.002, 90.37, 510.963], \"page_rect\": [0.0, 0.0, 595.28, 841.89], \"font_size\": 12.0, \"font\": \"MicrosoftJhengHeiRegular\", \"ascii_tokens\": [], \"cjk_char_count\": 4, \"preserve_tokens\": [], \"layout_hint\": \"short_label\"}, {\"unit_id\": \"p173_b12_l1\", \"page_index\": 173, \"block_id\": 12, \"line_index\": 1, \"source_text\": \"英國⽔災數據以2021年為基準考慮當前潮汐、河流和地⾯⽔災風險。⽔\", \"bbox\": [42.37, 511.145, 290.338, 521.785], \"page_rect\": [0.0, 0.0, 595.28, 841.89], \"font_size\": 8.0, \"font\": \"MicrosoftJhengHeiRegular\", \"ascii_tokens\": [], \"cjk_char_count\": 23, \"preserve_tokens\": [], \"layout_hint\": \"body\"}, {\"unit_id\": \"p173_b12_l2\", \"page_index\": 173, \"block_id\": 12, \"line_index\": 2, \"source_text\": \"災風險評分介乎0⾄100，以100評分為最⾼風險。⽔災風險等級根據平\", \"bbox\": [42.37, 520.745, 288.154, 531.385], \"page_rect\": [0.0, 0.0, 595.28, 841.89], \"font_size\": 8.0, \"font\": \"MicrosoftJhengHeiRegular\", \"ascii_tokens\": [], \"cjk_char_count\": 22, \"preserve_tokens\": [{\"type\": \"currency_amount\", \"value\": \"100\"}], \"layout_hint\": \"body\"}, {\"unit_id\": \"p173_b12_l3\", \"page_index\": 173, \"block_id\": 12, \"line_index\": 3, \"source_text\": \"均年度損失釐定，相關損失數字運⽤⽔災頻率、洪⽔深度和⽔災事件發\", \"bbox\": [42.37, 530.345, 287.97, 540.985], \"page_rect\": [0.0, 0.0, 595.28, 841.89], \"font_size\": 8.0, \"font\": \"MicrosoftJhengHeiRegular\", \"ascii_tokens\": [], \"cjk_char_count\": 25, \"preserve_tokens\": [], \"layout_hint\": \"body\"}, {\"unit_id\": \"p173_b12_l4\", \"page_index\": 173, \"block_id\": 12, \"line_index\": 4, \"source_text\": \"⽣機率計算得出。根據可得數據，英國業務按揭組合以結⽋計3.6%屬於\", \"bbox\": [42.37, 539.945, 289.954, 550.585], \"page_rect\": [0.0, 0.0, 595.28, 841.89], \"font_size\": 8.0, \"font\": \"MicrosoftJhengHeiRegular\", \"ascii_tokens\": [], \"cjk_char_count\": 25, \"preserve_tokens\": [{\"type\": \"percentage\", \"value\": \"3.6%\"}], \"layout_hint\": \"body\"}, {\"unit_id\": \"p173_b12_l5\", \"page_index\": 173, \"block_id\": 12, \"line_index\": 5, \"source_text\": \"極⾼／⾼⽔災風險。按地區計算，⼤倫敦和東南部是風險承擔最⾼的地\", \"bbox\": [42.37, 549.545, 287.97, 560.185], \"page_rect\": [0.0, 0.0, 595.28, 841.89], \"font_size\": 8.0, \"font\": \"MicrosoftJhengHeiRegular\", \"ascii_tokens\": [], \"cjk_char_count\": 23, \"preserve_tokens\": [], \"layout_hint\": \"body\"}, {\"unit_id\": \"p173_b12_l6\", \"page_index\": 173, \"block_id\": 12, \"line_index\": 6, \"source_text\": \"區。\", \"bbox\": [42.37, 559.145, 58.29, 569.785], \"page_rect\": [0.0, 0.0, 595.28, 841.89], \"font_size\": 8.0, \"font\": \"MicrosoftJhengHeiRegular\", \"ascii_tokens\": [], \"cjk_char_count\": 1, \"preserve_tokens\": [], \"layout_hint\": \"short_label\"}, {\"unit_id\": \"p173_b13_l0\", \"page_index\": 173, \"block_id\": 13, \"line_index\": 0, \"source_text\": \"Ñ 有關香港實體風險的資料，請參閱第176⾴境況分析⼀節。\", \"bbox\": [304.57, 204.31, 496.069, 214.559], \"page_rect\": [0.0, 0.0, 595.28, 841.89], \"font_size\": 9.0, \"font\": \"Wingdings3\", \"ascii_tokens\": [], \"cjk_char_count\": 20, \"preserve_tokens\": [], \"layout_hint\": \"body\"}, {\"unit_id\": \"p173_b14_l0\", \"page_index\": 173, \"block_id\": 14, \"line_index\": 0, \"source_text\": \"過渡風險\", \"bbox\": [304.57, 218.552, 352.57, 234.513], \"page_rect\": [0.0, 0.0, 595.28, 841.89], \"font_size\": 12.0, \"font\": \"MicrosoftJhengHeiRegular\", \"ascii_tokens\": [], \"cjk_char_count\": 4, \"preserve_tokens\": [], \"layout_hint\": \"short_label\"}, {\"unit_id\": \"p173_b14_l1\", \"page_index\": 173, \"block_id\": 14, \"line_index\": 1, \"source_text\": \"零售按揭貸款的過渡風險指由於向低碳經濟調整⽽導致物業價值潛在損\", \"bbox\": [304.57, 234.695, 550.17, 245.335], \"page_rect\": [0.0, 0.0, 595.28, 841.89], \"font_size\": 8.0, \"font\": \"MicrosoftJhengHeiRegular\", \"ascii_tokens\": [], \"cjk_char_count\": 30, \"preserve_tokens\": [], \"layout_hint\": \"body\"}, {\"unit_id\": \"p173_b14_l2\", \"page_index\": 173, \"block_id\": 14, \"line_index\": 2, \"source_text\": \"失及／或客⼾財務減值的風險。上述影響的例⼦包括能源價格變化以及\", \"bbox\": [304.57, 244.295, 550.17, 254.935], \"page_rect\": [0.0, 0.0, 595.28, 841.89], \"font_size\": 8.0, \"font\": \"MicrosoftJhengHeiRegular\", \"ascii_tokens\": [], \"cjk_char_count\": 27, \"preserve_tokens\": [], \"layout_hint\": \"body\"}, {\"unit_id\": \"p173_b14_l3\", \"page_index\": 173, \"block_id\": 14, \"line_index\": 3, \"source_text\": \"政府不斷修訂能源效益標準法規。\", \"bbox\": [304.57, 253.895, 423.45, 264.535], \"page_rect\": [0.0, 0.0, 595.28, 841.89], \"font_size\": 8.0, \"font\": \"MicrosoftJhengHeiRegular\", \"ascii_tokens\": [], \"cjk_char_count\": 14, \"preserve_tokens\": [], \"layout_hint\": \"short_label\"}, {\"unit_id\": \"p173_b15_l0\", \"page_index\": 173, \"block_id\": 15, \"line_index\": 0, \"source_text\": \"英國⽅⾯，我們監控各項物業的能源效益認證評級，從A級（最⾼效\", \"bbox\": [304.57, 269.995, 539.794, 280.635], \"page_rect\": [0.0, 0.0, 595.28, 841.89], \"font_size\": 8.0, \"font\": \"MicrosoftJhengHeiRegular\", \"ascii_tokens\": [\"A\"], \"cjk_char_count\": 23, \"preserve_tokens\": [], \"layout_hint\": \"body\"}, {\"unit_id\": \"p173_b15_l1\", \"page_index\": 173, \"block_id\": 15, \"line_index\": 1, \"source_text\": \"益）⾄G級（最低效益）不等，因為該能源效益認證普遍⽤於過渡風險\", \"bbox\": [304.57, 279.595, 548.082, 290.235], \"page_rect\": [0.0, 0.0, 595.28, 841.89], \"font_size\": 8.0, \"font\": \"MicrosoftJhengHeiRegular\", \"ascii_tokens\": [\"G\"], \"cjk_char_count\": 24, \"preserve_tokens\": [], \"layout_hint\": \"body\"}, {\"unit_id\": \"p173_b15_l2\", \"page_index\": 173, \"block_id\": 15, \"line_index\": 2, \"source_text\": \"指標。所有英國出租物業的能源效益認證評級最低須達E級。我們追蹤\", \"bbox\": [304.57, 289.195, 546.522, 299.835], \"page_rect\": [0.0, 0.0, 595.28, 841.89], \"font_size\": 8.0, \"font\": \"MicrosoftJhengHeiRegular\", \"ascii_tokens\": [\"E\"], \"cjk_char_count\": 28, \"preserve_tokens\": [], \"layout_hint\": \"body\"}, {\"unit_id\": \"p173_b15_l3\", \"page_index\": 173, \"block_id\": 15, \"line_index\": 3, \"source_text\": \"⾃住物業和出租物業的能源效益認證評級。環境、社會及管治資料庫詳\", \"bbox\": [304.57, 298.795, 550.17, 309.435], \"page_rect\": [0.0, 0.0, 595.28, 841.89], \"font_size\": 8.0, \"font\": \"MicrosoftJhengHeiRegular\", \"ascii_tokens\": [], \"cjk_char_count\": 28, \"preserve_tokens\": [], \"layout_hint\": \"body\"}, {\"unit_id\": \"p173_b15_l4\", \"page_index\": 173, \"block_id\": 15, \"line_index\": 4, \"source_text\": \"述集團現⾏的能源效益認證狀況。我們為求記錄完整，假如並無當前的\", \"bbox\": [304.57, 308.395, 550.17, 319.035], \"page_rect\": [0.0, 0.0, 595.28, 841.89], \"font_size\": 8.0, \"font\": \"MicrosoftJhengHeiRegular\", \"ascii_tokens\": [], \"cjk_char_count\": 28, \"preserve_tokens\": [], \"layout_hint\": \"body\"}, {\"unit_id\": \"p173_b15_l5\", \"page_index\": 173, \"block_id\": 15, \"line_index\": 5, \"source_text\": \"能源效益認證記錄，則以到期屆滿的能源效益認證為準。按貸款結⽋計\", \"bbox\": [304.57, 317.994, 550.17, 328.635], \"page_rect\": [0.0, 0.0, 595.28, 841.89], \"font_size\": 8.0, \"font\": \"MicrosoftJhengHeiRegular\", \"ascii_tokens\": [], \"cjk_char_count\": 28, \"preserve_tokens\": [], \"layout_hint\": \"body\"}, {\"unit_id\": \"p173_b15_l6\", \"page_index\": 173, \"block_id\": 15, \"line_index\": 6, \"source_text\": \"算，⾃住物業85.3%持有有效的能源效益認證／到期認證，其中41%物\", \"bbox\": [304.57, 327.594, 549.01, 338.235], \"page_rect\": [0.0, 0.0, 595.28, 841.89], \"font_size\": 8.0, \"font\": \"MicrosoftJhengHeiRegular\", \"ascii_tokens\": [], \"cjk_char_count\": 22, \"preserve_tokens\": [{\"type\": \"percentage\", \"value\": \"85.3%\"}, {\"type\": \"percentage\", \"value\": \"41%\"}], \"layout_hint\": \"body\"}, {\"unit_id\": \"p173_b15_l7\", \"page_index\": 173, \"block_id\": 15, \"line_index\": 7, \"source_text\": \"業屬能源效益認證A⾄C級。⾄於出租物業，按貸款結⽋計算83.1%物業\", \"bbox\": [304.57, 337.194, 551.594, 347.835], \"page_rect\": [0.0, 0.0, 595.28, 841.89], \"font_size\": 8.0, \"font\": \"MicrosoftJhengHeiRegular\", \"ascii_tokens\": [\"A\", \"C\"], \"cjk_char_count\": 22, \"preserve_tokens\": [{\"type\": \"percentage\", \"value\": \"83.1%\"}], \"layout_hint\": \"body\"}, {\"unit_id\": \"p173_b15_l8\", \"page_index\": 173, \"block_id\": 15, \"line_index\": 8, \"source_text\": \"持有有效的能源效益認證／到期認證，其中60.2%物業屬能源效益認證\", \"bbox\": [304.57, 346.794, 548.786, 357.435], \"page_rect\": [0.0, 0.0, 595.28, 841.89], \"font_size\": 8.0, \"font\": \"MicrosoftJhengHeiRegular\", \"ascii_tokens\": [], \"cjk_char_count\": 26, \"preserve_tokens\": [{\"type\": \"percentage\", \"value\": \"60.2%\"}], \"layout_hint\": \"body\"}, {\"unit_id\": \"p173_b15_l9\", \"page_index\": 173, \"block_id\": 15, \"line_index\": 9, \"source_text\": \"A⾄C級。我們將持續監察能源效益認證評級的情況，並密切關注政府\", \"bbox\": [304.57, 356.395, 545.058, 367.035], \"page_rect\": [0.0, 0.0, 595.28, 841.89], \"font_size\": 8.0, \"font\": \"MicrosoftJhengHeiRegular\", \"ascii_tokens\": [\"A\", \"C\"], \"cjk_char_count\": 26, \"preserve_tokens\": [], \"layout_hint\": \"body\"}, {\"unit_id\": \"p173_b15_l10\", \"page_index\": 173, \"block_id\": 15, \"line_index\": 10, \"source_text\": \"相關法規的演變，這是建築物減碳的關鍵因素。\", \"bbox\": [304.57, 365.995, 470.97, 376.635], \"page_rect\": [0.0, 0.0, 595.28, 841.89], \"font_size\": 8.0, \"font\": \"MicrosoftJhengHeiRegular\", \"ascii_tokens\": [], \"cjk_char_count\": 19, \"preserve_tokens\": [], \"layout_hint\": \"short_label\"}, {\"unit_id\": \"p173_b16_l0\", \"page_index\": 173, \"block_id\": 16, \"line_index\": 0, \"source_text\": \"Ñ 有關英國零售按揭組合的⽔災風險、能源效益認證分項及平均期限的詳情，\", \"bbox\": [304.57, 382.16, 546.91, 392.408], \"page_rect\": [0.0, 0.0, 595.28, 841.89], \"font_size\": 9.0, \"font\": \"Wingdings3\", \"ascii_tokens\": [], \"cjk_char_count\": 30, \"preserve_tokens\": [], \"layout_hint\": \"body\"}, {\"unit_id\": \"p173_b16_l1\", \"page_index\": 173, \"block_id\": 16, \"line_index\": 1, \"source_text\": \"請參閱載於 www.hsbc.com/esg 的《環境、社會及管治資料集》。\", \"bbox\": [315.91, 391.53, 523.131, 400.841], \"page_rect\": [0.0, 0.0, 595.28, 841.89], \"font_size\": 7.0, \"font\": \"MicrosoftJhengHeiRegular\", \"ascii_tokens\": [\"www.hsbc.com/esg\"], \"cjk_char_count\": 16, \"preserve_tokens\": [], \"layout_hint\": \"body\"}, {\"unit_id\": \"p173_b17_l0\", \"page_index\": 173, \"block_id\": 17, \"line_index\": 0, \"source_text\": \"財資風險\", \"bbox\": [304.57, 406.266, 356.57, 423.557], \"page_rect\": [0.0, 0.0, 595.28, 841.89], \"font_size\": 13.0, \"font\": \"MicrosoftJhengHeiRegular\", \"ascii_tokens\": [], \"cjk_char_count\": 4, \"preserve_tokens\": [], \"layout_hint\": \"short_label\"}, {\"unit_id\": \"p173_b18_l0\", \"page_index\": 173, \"block_id\": 18, \"line_index\": 0, \"source_text\": \"氣候風險可能透過監管規定增加和客⼾⾏為轉變影響財資風險，繼⽽可\", \"bbox\": [304.57, 423.794, 550.17, 434.435], \"page_rect\": [0.0, 0.0, 595.28, 841.89], \"font_size\": 8.0, \"font\": \"MicrosoftJhengHeiRegular\", \"ascii_tokens\": [], \"cjk_char_count\": 27, \"preserve_tokens\": [], \"layout_hint\": \"body\"}, {\"unit_id\": \"p173_b18_l1\", \"page_index\": 173, \"block_id\": 18, \"line_index\": 1, \"source_text\": \"能加劇存款外流。氣候風險亦可能影響利率，繼⽽影響資產負債表的重\", \"bbox\": [304.57, 433.395, 550.17, 444.035], \"page_rect\": [0.0, 0.0, 595.28, 841.89], \"font_size\": 8.0, \"font\": \"MicrosoftJhengHeiRegular\", \"ascii_tokens\": [], \"cjk_char_count\": 28, \"preserve_tokens\": [], \"layout_hint\": \"body\"}, {\"unit_id\": \"p173_b18_l2\", \"page_index\": 173, \"block_id\": 18, \"line_index\": 2, \"source_text\": \"新定價狀況。\", \"bbox\": [304.57, 442.995, 352.17, 453.635], \"page_rect\": [0.0, 0.0, 595.28, 841.89], \"font_size\": 8.0, \"font\": \"MicrosoftJhengHeiRegular\", \"ascii_tokens\": [], \"cjk_char_count\": 5, \"preserve_tokens\": [], \"layout_hint\": \"short_label\"}, {\"unit_id\": \"p173_b19_l0\", \"page_index\": 173, \"block_id\": 19, \"line_index\": 0, \"source_text\": \"我們以信貸風險、交易風險及營運風險為重點，評估氣候變化對資本的\", \"bbox\": [304.57, 459.095, 550.17, 469.735], \"page_rect\": [0.0, 0.0, 595.28, 841.89], \"font_size\": 8.0, \"font\": \"MicrosoftJhengHeiRegular\", \"ascii_tokens\": [], \"cjk_char_count\": 29, \"preserve_tokens\": [], \"layout_hint\": \"body\"}, {\"unit_id\": \"p173_b19_l1\", \"page_index\": 173, \"block_id\": 19, \"line_index\": 1, \"source_text\": \"影響，並且對內部資本規劃緩衝進⾏敏感度分析，作為集團內部資本充\", \"bbox\": [304.57, 468.695, 550.17, 479.335], \"page_rect\": [0.0, 0.0, 595.28, 841.89], \"font_size\": 8.0, \"font\": \"MicrosoftJhengHeiRegular\", \"ascii_tokens\": [], \"cjk_char_count\": 28, \"preserve_tokens\": [], \"layout_hint\": \"body\"}, {\"unit_id\": \"p173_b19_l2\", \"page_index\": 173, \"block_id\": 19, \"line_index\": 2, \"source_text\": \"⾜程度評估程序⼀環。\", \"bbox\": [304.57, 478.295, 383.85, 488.935], \"page_rect\": [0.0, 0.0, 595.28, 841.89], \"font_size\": 8.0, \"font\": \"MicrosoftJhengHeiRegular\", \"ascii_tokens\": [], \"cjk_char_count\": 7, \"preserve_tokens\": [], \"layout_hint\": \"short_label\"}, {\"unit_id\": \"p173_b20_l0\", \"page_index\": 173, \"block_id\": 20, \"line_index\": 0, \"source_text\": \"我們評估氣候風險如何影響集團流動資⾦狀況，作為集團內部流動資⾦\", \"bbox\": [304.57, 494.395, 550.17, 505.035], \"page_rect\": [0.0, 0.0, 595.28, 841.89], \"font_size\": 8.0, \"font\": \"MicrosoftJhengHeiRegular\", \"ascii_tokens\": [], \"cjk_char_count\": 28, \"preserve_tokens\": [], \"layout_hint\": \"body\"}, {\"unit_id\": \"p173_b20_l1\", \"page_index\": 173, \"block_id\": 20, \"line_index\": 1, \"source_text\": \"充⾜程度評估程序⼀環。\", \"bbox\": [304.57, 503.995, 391.77, 514.635], \"page_rect\": [0.0, 0.0, 595.28, 841.89], \"font_size\": 8.0, \"font\": \"MicrosoftJhengHeiRegular\", \"ascii_tokens\": [], \"cjk_char_count\": 8, \"preserve_tokens\": [], \"layout_hint\": \"short_label\"}]. Terminology policy: {\"source\": \"current-run source units only\", \"known_reference_translation_allowed\": false}. Before persisting prompt/model/decision artifacts, the executor must have produced a workspace boundary report at \"docs/reports/round15/translation_batches/batch_0086.workspace_boundary.json\" with workspace_boundary_verdict=PASS for all planned batch output paths. Output one record per source unit in this batch only. Do not output placeholders or meta descriptions. Forbidden target patterns include 'This line reports/describes/lists...', '本行说明/列示/报告...', '当前页的财务报告、治理或业务信息', and any instruction text like 'preserve figures/markers' or '保留数值与标记'. Preserve typed tokens in preserve_tokens but do not mention the preservation instruction in the translation. Put the full semantic target text in \"translation_en\" and translation_target_text. For units whose text_role/layout_hint is compact_label, short_label, table_cell, legend, vertical_nav, chart_label, or table_header, layout_variants is required and must include the matching target-language suffix keys such as compact_label_zh/compact_label_en, short_label_zh/short_label_en, table_cell_zh/table_cell_en, legend_zh/legend_en, vertical_nav_zh/vertical_nav_en, plus display_zh/display_en when useful. Variants must preserve the same concept as the full target text and may use domain-standard abbreviations from the supplied source/terminology only; do not invent document-specific shorthand. Persist the raw model output to \"docs/reports/round15/translation_batches/batch_0086.model_output.json\" before validation.",
  "slot_values_ref": "docs/reports/round15/translation_batches/batch_0086.slot_values.json",
  "created_at": "2026-07-07 03:04:35"
}